{
    "!": [
        "!"
    ],
    "!\"": [
        "!\""
    ],
    "\"": [
        "\""
    ],
    "(": [
        "("
    ],
    ")": [
        ")"
    ],
    ",": [
        ","
    ],
    ",»": [
        ",»"
    ],
    ".": [
        "."
    ],
    ".\"": [
        ".\""
    ],
    "..": [
        ".."
    ],
    "...": [
        "..."
    ],
    ".»": [
        ".»"
    ],
    "00": [
        "00"
    ],
    "01": [
        "01"
    ],
    "02": [
        "02"
    ],
    "03": [
        "03"
    ],
    "04": [
        "04"
    ],
    "05": [
        "05"
    ],
    "06": [
        "06"
    ],
    "07": [
        "07"
    ],
    "18": [
        "18"
    ],
    "20": [
        "20"
    ],
    "28": [
        "28"
    ],
    "30": [
        "30"
    ],
    "32": [
        "32"
    ],
    "34": [
        "34"
    ],
    "39": [
        "39"
    ],
    "47": [
        "47"
    ],
    "4Ӏ": [
        "41"
    ],
    "59": [
        "59"
    ],
    ":": [
        ":"
    ],
    ":\"": [
        ":\""
    ],
    "?": [
        "?"
    ],
    "?\"": [
        "?\""
    ],
    "?)": [
        "?)"
    ],
    "?»": [
        "?»"
    ],
    "Mадни": [
        "more-FOC"
    ],
    "«": [
        "«"
    ],
    "»": [
        "»"
    ],
    "»,": [
        "»,"
    ],
    "».": [
        "»."
    ],
    "А": [
        "that"
    ],
    "АФия": [
        "Afiya"
    ],
    "Абур": [
        "they"
    ],
    "Абуриз": [
        "they-OBL-DAT"
    ],
    "Абурикай": [
        "they-ERG-SUB-EL"
    ],
    "Абурни": [
        "they-FOC"
    ],
    "Абуру": [
        "they-ERG"
    ],
    "Абурувай": [
        "obl.stm-ABS.PL-ERG-AD-EL"
    ],
    "Авуна": [
        "make,.do-AOR"
    ],
    "Агатна": [
        "approch-AOC"
    ],
    "Адаз": [
        "he-DAT",
        "that-OBL-DAT"
    ],
    "Адалай": [
        "it-SPSS-EL"
    ],
    "Адан": [
        "he-GEN"
    ],
    "Азербайджан": [
        "Azerbaijan"
    ],
    "Азербайджанда": [
        "Azerbaijan-INESS"
    ],
    "Азербайджанни": [
        "Azerbaijan-FOC"
    ],
    "Акатда": [
        "fall-ENT"
    ],
    "АкуртӀа": [
        "seen-COND",
        "hit-AOP-COND",
        "saw"
    ],
    "Акъадарда": [
        "mount.ENT"
    ],
    "Акъадра": [
        "mount.IMPV"
    ],
    "Акъахда": [
        "mount.IMPV-INESS"
    ],
    "АкӀ": [
        "like.that"
    ],
    "Алатайла": [
        "passing.TEMP-PST-TEMP"
    ],
    "Алатда": [
        "pass-ENT"
    ],
    "Алатна": [
        "pass-AOC"
    ],
    "Аллагь": [
        "Allah"
    ],
    "Аллагьдиз": [
        "Allah-OBL-DAT"
    ],
    "Алцурарда": [
        "decieved.ENT-ENT"
    ],
    "Аляскадин": [
        "Alyaska's-ERG-GEN"
    ],
    "Америкадин": [
        "America's-ERG-GEN"
    ],
    "Ана": [
        "there"
    ],
    "Анадырдани": [
        "Anadyr.from-INESS-FOC"
    ],
    "Анадырдиз": [
        "Anadyr.from-DIR-DAT",
        "Anadyr.from-ERG-DAT"
    ],
    "Анай": [
        "there.from",
        "there-PST"
    ],
    "Анжах": [
        "only"
    ],
    "Асеф": [
        "Asef"
    ],
    "Атайла": [
        "coming-PST-TEMP"
    ],
    "Атана": [
        "come-AOC"
    ],
    "Атанва": [
        "coming-PERF"
    ],
    "АтӀуз": [
        "cutting.IMC-DAT"
    ],
    "АтӀутӀ": [
        "cut.IMPV"
    ],
    "Ахпа": [
        "then",
        "After"
    ],
    "Ахпани": [
        "After-FOC"
    ],
    "Ахтынский": [
        "Akhtinsky"
    ],
    "Ахъаюнмаз": [
        "release.IMMANT-IMC"
    ],
    "Ахьтин": [
        "like.that"
    ],
    "Ашкъидин": [
        "love-ERG-GEN"
    ],
    "Ашукь": [
        "ashuq"
    ],
    "Аялар": [
        "child-PL"
    ],
    "БТР": [
        "APC"
    ],
    "Бакида": [
        "Baku-INESS"
    ],
    "Бакидиз": [
        "Baku-ERG-DAT"
    ],
    "Бакуда": [
        "Baku-INESS"
    ],
    "Бакудиз": [
        "Baku.to-DIR-DAT"
    ],
    "БалкӀан": [
        "horse"
    ],
    "БалкӀанди": [
        "horse-ERG"
    ],
    "БацӀ": [
        "Bats"
    ],
    "Баш~уьсте": [
        "IT.WILL.BE.DONE"
    ],
    "Бебир": [
        "Bebir"
    ],
    "Безханум": [
        "Bezkhanum"
    ],
    "Безханума": [
        "Bezkhanum-ERG"
    ],
    "Безхануман": [
        "Bezkhanum's"
    ],
    "Безханумахъ": [
        "Bezkhanum-ERG-POESS"
    ],
    "Белке": [
        "maybe"
    ],
    "Бельгиядиз": [
        "Belgium-DIR-DAT"
    ],
    "Берлиндай": [
        "Berlin-INELAT"
    ],
    "Берлиндиз": [
        "Berlin-DIR-DAT"
    ],
    "Бес": [
        "And.but",
        "but"
    ],
    "Бешир": [
        "Beshir"
    ],
    "Ва": [
        "and"
    ],
    "Вад": [
        "five"
    ],
    "Ваз": [
        "2sg-DAT",
        "you"
    ],
    "Вак": [
        "you.with"
    ],
    "Вахт": [
        "time"
    ],
    "Вач": [
        "go.IMPV"
    ],
    "Ваъ": [
        "no"
    ],
    "Вегьена": [
        "threw-AOC"
    ],
    "Везиятда": [
        "condition-INESS"
    ],
    "Велибег": [
        "Velibeg"
    ],
    "Велибеган": [
        "Velibeg-ERG-GEN",
        "Velibeg-GEN"
    ],
    "Ви": [
        "2sg.gen"
    ],
    "Вил": [
        "eye"
    ],
    "Вири": [
        "all"
    ],
    "Вирини": [
        "Everything-FOC"
    ],
    "Вич": [
        "himself"
    ],
    "Вичизни": [
        "himself-ERG-DAT-FOC"
    ],
    "Вичин": [
        "he-GEN",
        "himself-ERG-GEN",
        "himself-OBL-GEN"
    ],
    "Вичини": [
        "himself-ERG-FOC"
    ],
    "Вични": [
        "himself-FOC"
    ],
    "Вобщем": [
        "anyway"
    ],
    "Вообще": [
        "commonly"
    ],
    "Вот": [
        "there"
    ],
    "Ву": [
        "you"
    ],
    "Вун": [
        "2sg.abs"
    ],
    "Вуна": [
        "2sg.erg",
        "2sg.abs-OBL",
        "you-ERG"
    ],
    "Вунани": [
        "2sg.abs-ERG-FOC"
    ],
    "Вуч": [
        "what"
    ],
    "Вучиз": [
        "what-ERG-DAT"
    ],
    "Гагьатзава": [
        "escape-IMPF"
    ],
    "Гада": [
        "boy"
    ],
    "Гададизни": [
        "boy-ERG-DAT-Q"
    ],
    "Гададини": [
        "guy.ERG.and",
        "boy-DIR-GEN-ERG"
    ],
    "Гадани": [
        "boy-FOC"
    ],
    "Галатна": [
        "tire-AOC"
    ],
    "Гатдамаз": [
        "escape-ENT-IMMANT"
    ],
    "Гаф": [
        "word"
    ],
    "Гила": [
        "now"
    ],
    "Голландиядиз": [
        "Holland-ERG-DAT"
    ],
    "Гуржистандиз": [
        "Georgia-DIR-DAT"
    ],
    "Гъел": [
        "plough"
    ],
    "Гъилин": [
        "hand-OBL-GEN"
    ],
    "Гьа": [
        "that,.the.same",
        "today"
    ],
    "Гьа~бередани": [
        "AT.THAT.TIME-INESS-FOC"
    ],
    "Гьаа": [
        "Yes"
    ],
    "Гьабурни": [
        "them-Q"
    ],
    "Гьагь": [
        "yes"
    ],
    "Гьада": [
        "then"
    ],
    "Гьадазни": [
        "she-DAT-FOC"
    ],
    "Гьадалай": [
        "today-OBL-SUPER-EL",
        "she-TEMP-AOP"
    ],
    "Гьаджи": [
        "Hadji"
    ],
    "Гьакъикъетда": [
        "really-INESS"
    ],
    "ГьакӀ": [
        "like.that",
        "in.this.way"
    ],
    "Гьамани": [
        "it.also-FOC"
    ],
    "Гьана": [
        "there"
    ],
    "Гьанал": [
        "that-OBL-SPSS"
    ],
    "Гьар": [
        "every"
    ],
    "Гьарада": [
        "everybody-ERG"
    ],
    "Гьетта": [
        "also"
    ],
    "Гьим": [
        "that.one"
    ],
    "Гьинай": [
        "where-PST"
    ],
    "Гьиниз": [
        "where"
    ],
    "Гьисятда": [
        "now-INESS"
    ],
    "Гьуьлуьн": [
        "sea-OBL-GEN"
    ],
    "Дежурныйдиз": [
        "on..duty-ERG-DAT"
    ],
    "Дербентда": [
        "Derbent.in-INESS"
    ],
    "Дербентдин": [
        "Derbent.in-OBL-GEN"
    ],
    "Джагьан": [
        "Jahan"
    ],
    "Джафер": [
        "Jaffer"
    ],
    "Дидедин": [
        "mother-DIR-GEN"
    ],
    "Дуьз": [
        "right"
    ],
    "Егьена": [
        "is.putting-AOR"
    ],
    "Еке": [
        "great"
    ],
    "Жаваб": [
        "answer"
    ],
    "Жамаатди": [
        "people-DIR"
    ],
    "Жемятдизни": [
        "people.to.and"
    ],
    "Жи": [
        "1pl.gen"
    ],
    "За": [
        "1sg.ERG"
    ],
    "Зав": [
        "1sg.ERG-AD"
    ],
    "Заз": [
        "1sg.ERG-DAT"
    ],
    "Зазни": [
        "1sg.ERG-DAT-FOC"
    ],
    "Закай": [
        "1sg.ERG-SUB-EL"
    ],
    "Зани": [
        "1sg.ERG-FOC"
    ],
    "Занни": [
        "1sg.ERG-GEN-FOC"
    ],
    "Зейналабдин": [
        "Zeynalabdin"
    ],
    "Зейнеддинан": [
        "Zeynaddin-ERG-GEN"
    ],
    "Зерна": [
        "run"
    ],
    "Зи": [
        "1sg.gen"
    ],
    "Зу": [
        "my"
    ],
    "Зун": [
        "1sg.abs"
    ],
    "Зунни": [
        "1sg.abs-FOC"
    ],
    "И": [
        "this"
    ],
    "И~арада": [
        "AT.THIS.MOMENT-INESS",
        "AT.THIS.MOMENT"
    ],
    "Ибурикай": [
        "they.from"
    ],
    "Ибурни": [
        "they-FOC",
        "they.and"
    ],
    "Ибуру": [
        "these-ERG"
    ],
    "Ибурузни": [
        "these-ERG-DAT-FOC",
        "they.to.also"
    ],
    "Ибуруни": [
        "They.and",
        "these-ERG-Q",
        "these-ERG-FOC"
    ],
    "Иван": [
        "night-ERG-GEN"
    ],
    "Ида": [
        "her",
        "he.from"
    ],
    "Идаз": [
        "her-DAT",
        "he.also-DAT"
    ],
    "Идазни": [
        "he.also-DAT-FOC",
        "her-DAT-Q"
    ],
    "Идакай": [
        "she.and-SBSS-INELAT"
    ],
    "Идан": [
        "he.also-GEN"
    ],
    "Идани": [
        "her-FOC",
        "her-AND",
        "he.and",
        "her-FOCUS"
    ],
    "Идрис": [
        "Idris"
    ],
    "Ийида": [
        "make-ENT"
    ],
    "Ийимир": [
        "make-PROH"
    ],
    "Икьван": [
        "so.much"
    ],
    "ИкӀ": [
        "like.this"
    ],
    "Им": [
        "he",
        "this"
    ],
    "Има": [
        "this.one"
    ],
    "Имани": [
        "this-Q",
        "this-FOC"
    ],
    "Имни": [
        "he-FOC"
    ],
    "Имран": [
        "Imran"
    ],
    "Имрана": [
        "Imran-ERG"
    ],
    "Ина": [
        "here"
    ],
    "Инай": [
        "here-PST"
    ],
    "Инални": [
        "here-FOC"
    ],
    "Иниз": [
        "here-DAT"
    ],
    "Исабалади": [
        "Isabala-ERG"
    ],
    "Исабаладив": [
        "Isabala-DIR-AD"
    ],
    "Исабаладин": [
        "Isabala-DIR-GEN"
    ],
    "Иси": [
        "Isi"
    ],
    "Исятда": [
        "now-INESS"
    ],
    "Йисан": [
        "year's"
    ],
    "Кани": [
        "dear-ERG",
        "want-ERG"
    ],
    "Канивал": [
        "want-ERG-PURP"
    ],
    "Катна": [
        "running.AOC"
    ],
    "Квез": [
        "2pl.dat"
    ],
    "КилигайтӀа": [
        "look-AOP-COND"
    ],
    "КицӀ": [
        "dog"
    ],
    "Крарикай": [
        "things-ERG-SBSS-INELAT"
    ],
    "Къазах": [
        "kazakh"
    ],
    "Къазахстанда": [
        "Kazakhstan.in-INESS"
    ],
    "Къамни": [
        "sadness.also-FOC"
    ],
    "Къанивилин": [
        "want-ERG-PL-ERG-GEN"
    ],
    "Къарлай": [
        "days-SPSS-EL"
    ],
    "Къачуз": [
        "take-INF"
    ],
    "Къваззава": [
        "stayed-IMPF"
    ],
    "Къведа": [
        "come-ENT"
    ],
    "Къе": [
        "today"
    ],
    "Къеледиз": [
        "fortress-OBL-DAT"
    ],
    "Къеледин": [
        "fortress-OBL-GEN"
    ],
    "Къулухъ": [
        "after"
    ],
    "Кьве": [
        "two"
    ],
    "Кьвед~лагьай": [
        "SECOND"
    ],
    "Кьведаз": [
        "two-OBL-DAT"
    ],
    "Кьуьзуь": [
        "old"
    ],
    "КӀватӀна": [
        "to.gather-AOR"
    ],
    "КӀцар": [
        "Gusar"
    ],
    "Лагьана": [
        "say-AOR"
    ],
    "Лежет": [
        "Ledjet"
    ],
    "Лезгиярни": [
        "Lezgi-PL-FOC"
    ],
    "Лейли": [
        "Leyli"
    ],
    "Ленинграддин": [
        "Leningrad's-DIR-GEN",
        "Leningrad-ERG-GEN"
    ],
    "Ленинградом": [
        "Leningrad"
    ],
    "Литвада": [
        "Lithuania-INESS"
    ],
    "Литвадиз": [
        "Lithuania-DIR-DAT"
    ],
    "Литвадин": [
        "Lithuania-DIR-GEN"
    ],
    "Лув": [
        "wing"
    ],
    "Лугьузва": [
        "say-IMPF"
    ],
    "Мадни": [
        "more-FOC"
    ],
    "Мама": [
        "mother"
    ],
    "Мамани": [
        "mother-FOC"
    ],
    "Масадаз": [
        "sell-INESS-DAT"
    ],
    "Машин": [
        "car"
    ],
    "Мегьманан": [
        "Mehman's-OBL-GEN"
    ],
    "Межлис": [
        "event"
    ],
    "Межнун": [
        "Medjnun"
    ],
    "Миграгъ": [
        "Migragh",
        "Migrah"
    ],
    "Мицибуру": [
        "others-ERG"
    ],
    "Мугьубатдин": [
        "love-OBL-GEN"
    ],
    "На": [
        "you"
    ],
    "Назир": [
        "Nazir"
    ],
    "Накьвар": [
        "soil-AD-PL"
    ],
    "Насруллагь": [
        "Nasrullah"
    ],
    "Негъен": [
        "evening"
    ],
    "Но": [
        "But"
    ],
    "Новгородда": [
        "Novgorod.in-INESS"
    ],
    "Ну": [
        "well"
    ],
    "Нуьсрет": [
        "Nusret"
    ],
    "Нуьсретахъ": [
        "Nusret-ERG-POESS"
    ],
    "О": [
        "Too"
    ],
    "Огонь~Копида": [
        "OGON.KOPY.IN"
    ],
    "Он": [
        "he"
    ],
    "Она~гуьре": [
        "THERFORE"
    ],
    "Паекни": [
        "ration"
    ],
    "Палкан": [
        "horse"
    ],
    "Пара": [
        "very"
    ],
    "Паспортар": [
        "pasport-PL"
    ],
    "Писвал": [
        "evil-PURP"
    ],
    "Польшадай": [
        "Poland-INESS-PST",
        "Poland-INELAT"
    ],
    "Пуд": [
        "three"
    ],
    "Пятьдесят": [
        "fifty"
    ],
    "Рагьуллагь": [
        "Rahulla"
    ],
    "Рази": [
        "agree"
    ],
    "Рак": [
        "door"
    ],
    "Рекье": [
        "way-INESS"
    ],
    "Рехъ": [
        "road"
    ],
    "Россиядин": [
        "Russia-OBL-GEN"
    ],
    "Руслан": [
        "Ruslan"
    ],
    "Руш": [
        "girl"
    ],
    "Руша": [
        "girl-ERG"
    ],
    "Рушани": [
        "girl-ERG-FOC"
    ],
    "Рушарин": [
        "girl-PL-ERG-GEN"
    ],
    "Рушахъ": [
        "girl.with"
    ],
    "Рушни": [
        "girl-FOC"
    ],
    "СССР": [
        "USSR"
    ],
    "Са": [
        "one",
        "only"
    ],
    "Сад": [
        "one"
    ],
    "Сад~лагьана": [
        "SUDDENLY-AOR"
    ],
    "Садра": [
        "once"
    ],
    "Самур": [
        "\"Samur\"",
        "\"Samur'"
    ],
    "Сарах": [
        "once"
    ],
    "Себри": [
        "Sabri"
    ],
    "Себрилла": [
        "Sebrilla"
    ],
    "Себриллагьахъ": [
        "Sebrilla"
    ],
    "Севастопольда": [
        "Sevastopol-INESS"
    ],
    "Севастопольдиз": [
        "Sevastopol-ERG-DAT"
    ],
    "Севда": [
        "Sevda"
    ],
    "Седакъет": [
        "Sedaget"
    ],
    "Серинвал": [
        "cool-PURP"
    ],
    "Случайно": [
        "accidentally"
    ],
    "Советдин": [
        "Soviet-ERG-GEN"
    ],
    "Сонра": [
        "after"
    ],
    "Сонрани": [
        "after-FOC"
    ],
    "Суракьиз": [
        "asking"
    ],
    "Тагиев": [
        "Tagiyev"
    ],
    "Тагиева": [
        "Tagiyev-ERG"
    ],
    "Тагиеваз": [
        "Tagiyev-ERG-DAT"
    ],
    "Таниш": [
        "acquainted"
    ],
    "ТапарарзаватӀа": [
        "lie-IMPF-COND"
    ],
    "Твах": [
        "carry.IMPV"
    ],
    "Текче": [
        "only"
    ],
    "Техминан": [
        "About"
    ],
    "Трамплин": [
        "springboard"
    ],
    "Тухуда": [
        "take-INESS"
    ],
    "ТӀванлай": [
        "from.there"
    ],
    "ТӀимил": [
        "little"
    ],
    "Ун": [
        "yes"
    ],
    "Уъ": [
        "yes"
    ],
    "Фена": [
        "go-AOR",
        "go-AOC"
    ],
    "Фена-фена": [
        "go-AOR"
    ],
    "Фергьад": [
        "Ferhad"
    ],
    "Фида": [
        "go-ENT",
        "go-INESS",
        "go-FUT"
    ],
    "Фидайла": [
        "go-PST-TEMP"
    ],
    "Фидамаз": [
        "go.FUT-FUT-IMMANT"
    ],
    "Франциядай": [
        "France-INELAT"
    ],
    "Франциядиз": [
        "France-DIR-DAT"
    ],
    "Фу": [
        "bread"
    ],
    "Хвеши": [
        "happy"
    ],
    "Хкадарда": [
        "jumps-INESS"
    ],
    "Хтайла": [
        "return-PST-TEMP"
    ],
    "Хтана": [
        "return-AOR"
    ],
    "Хтуларни": [
        "grandchild-PL-FOC"
    ],
    "Худат": [
        "Khudat"
    ],
    "Хуьруьз": [
        "village-OBL-DAT"
    ],
    "Хъфена": [
        "go-AOR"
    ],
    "Хъфида": [
        "go-ENT"
    ],
    "Хырдаланда": [
        "Khyrdalan-INESS"
    ],
    "ХьайитӀа": [
        "be.AOP.COND"
    ],
    "Хьуй": [
        "Let.it.be"
    ],
    "Цайлапанрикай": [
        "lightning-OBL-SUB-EL"
    ],
    "ЦӀуьгъвенай": [
        "behind"
    ],
    "Чаз": [
        "1pl.gen-DAT"
    ],
    "Чан": [
        "dear",
        "soul"
    ],
    "Чи": [
        "1pl.gen"
    ],
    "Чка": [
        "place"
    ],
    "Чох~сагъол": [
        "THANK.YOU"
    ],
    "Чпивай": [
        "themselves-AD-EL"
    ],
    "Чпин": [
        "their.own"
    ],
    "Чукоткада": [
        "Chukotka-INESS"
    ],
    "Чун": [
        "1pl.abs"
    ],
    "Чунни": [
        "1pl.abs-FOC"
    ],
    "ЧӀехи": [
        "Oldest",
        "Big"
    ],
    "Ша": [
        "come"
    ],
    "Шагьдагъ": [
        "Shahdag"
    ],
    "Шагьдагъдин": [
        "Shahdag-OBL-GEN"
    ],
    "Шемседдинан": [
        "Shemseddin-OBL-GEN"
    ],
    "Ширин": [
        "Shirin"
    ],
    "Шоллардай": [
        "Shollar.from-INELAT"
    ],
    "Шуьбяддин": [
        "Shubyaddin"
    ],
    "Эвел": [
        "before"
    ],
    "Эвера": [
        "call?-ERG"
    ],
    "Эверда": [
        "call.IMPV-INESS"
    ],
    "ЭвецӀда": [
        "went.down.ENT-ENT"
    ],
    "Эвли": [
        "married"
    ],
    "Эгер": [
        "if"
    ],
    "Эгьтибарсуз": [
        "unfaithful"
    ],
    "Эй": [
        "hey"
    ],
    "Эйиб": [
        "shame"
    ],
    "ЭкъецӀна": [
        "appearing.AOC"
    ],
    "Элквена": [
        "turned-AOR"
    ],
    "Элкъвезва": [
        "turns-IMPF"
    ],
    "Элкъуьгъ": [
        "turn.back"
    ],
    "Элчиярни": [
        "matchmakers.also-PL-FOC"
    ],
    "Эскервиле": [
        "military.service",
        "military.service-INESS"
    ],
    "Эхир": [
        "after.all"
    ],
    "Эхирни": [
        "end-FOC"
    ],
    "Эхъвез": [
        "bathing-INF"
    ],
    "Юлдашарикай": [
        "friend-PL-OBL-SUB-EL"
    ],
    "Юсуф": [
        "Yusif"
    ],
    "Я": [
        "was",
        "hey"
    ],
    "Ядни": [
        "water-AND"
    ],
    "Яламадини": [
        "Yalama's-DIR-FOC",
        "Yalama's-DIR-Q"
    ],
    "Яни": [
        "cop-FOC"
    ],
    "Яргъал": [
        "far"
    ],
    "ЯхцӀур": [
        "fourty"
    ],
    "Яшамишда": [
        "live-ENT"
    ],
    "а": [
        "that"
    ],
    "абур": [
        "they",
        "obl.stm-ABS.PL"
    ],
    "абурал": [
        "obl.stm-ABS.PL-ERG-SPSS"
    ],
    "абури": [
        "they-ERG"
    ],
    "абуриз": [
        "they-ERG-DAT"
    ],
    "абурин": [
        "they-ERG-GEN"
    ],
    "абуруз": [
        "they-ERG-DAT"
    ],
    "ава": [
        "cop",
        "is"
    ],
    "аваз": [
        "is-DAT",
        "is-INF"
    ],
    "авазва": [
        "cop-IMPF"
    ],
    "авай": [
        "is-PTP",
        "is-AOP",
        "is-PST",
        "cop-PTP",
        "cop-PST"
    ],
    "авайбур": [
        "existed"
    ],
    "авайди": [
        "is-AOP-SBST",
        "is-PST-SBST",
        "cop-PTP-SBST"
    ],
    "авайла": [
        "is-AOP-TEMP",
        "is-PST-TEMP"
    ],
    "авани": [
        "is-FOC"
    ],
    "авариядиз": [
        "accident.into-OBL-DAT"
    ],
    "аватда": [
        "fell-INESS"
    ],
    "аватна": [
        "fall-AOR",
        "fell-AOR"
    ],
    "аватӀа": [
        "is-COND"
    ],
    "авач": [
        "is-NEG"
    ],
    "авачир": [
        "is-NEG.PST"
    ],
    "аваш": [
        "is-NEG"
    ],
    "авудна": [
        "taking.down.AOC"
    ],
    "авуна": [
        "make,.do-AOR",
        "make,.do-AOC"
    ],
    "агакьарна": [
        "pass.on-PL-AOR"
    ],
    "агакьда": [
        "pass.on-ENT"
    ],
    "агакьна": [
        "pass.on-AOC"
    ],
    "агатиз": [
        "approch-INF"
    ],
    "агъана": [
        "bring-AOC",
        "bring-AOR"
    ],
    "агъзур": [
        "100"
    ],
    "агъуз": [
        "down"
    ],
    "агь": [
        "moaning"
    ],
    "ада": [
        "he",
        "it"
    ],
    "адав": [
        "he-AD"
    ],
    "адаз": [
        "he-DAT",
        "that-OBL-DAT"
    ],
    "адакай": [
        "he-SBSS-INELAT"
    ],
    "адал": [
        "it-SPSS"
    ],
    "адан": [
        "he-GEN",
        "his"
    ],
    "адетар": [
        "tradtition-PL"
    ],
    "азербайджанар": [
        "azebaijanis-PL"
    ],
    "айир": [
        "made-AOP"
    ],
    "акакьда": [
        "reached.ENT-INESS"
    ],
    "акахьнавай": [
        "closer.us-PERF-PTP"
    ],
    "аквада": [
        "to.see-ENT"
    ],
    "аквазва": [
        "see.is-IMPF"
    ],
    "аквазвай": [
        "see.is-IMPF-AOP"
    ],
    "акван": [
        "look.HORT"
    ],
    "аку": [
        "look"
    ],
    "акуна": [
        "see-AOR",
        "hit-AOC",
        "see-AOC"
    ],
    "акунгаз": [
        "see.like"
    ],
    "акур": [
        "seen"
    ],
    "акурла": [
        "seen-TEMP"
    ],
    "акуртӀа": [
        "seen-COND",
        "seen"
    ],
    "акутӀа": [
        "look-COND"
    ],
    "акъадарда": [
        "mount.ENT"
    ],
    "акъадарна": [
        "mount.ENT-AOR"
    ],
    "акъат": [
        "apperance"
    ],
    "акъатзавач": [
        "apperance-IMPF-NEG"
    ],
    "акъатна": [
        "apperance-AOR",
        "apperance-AOC"
    ],
    "акъахна": [
        "mount.IMPV-AOR",
        "climbing-AOC"
    ],
    "акъвазарна": [
        "make.stopping-AOC"
    ],
    "акъвазва": [
        "to.stay-IMPF"
    ],
    "акъваздай": [
        "stop-ENT-PTP"
    ],
    "акъвезва": [
        "walk-IMPF"
    ],
    "акъвенва": [
        "walked-PERF"
    ],
    "акъудзава": [
        "get.out-IMPF"
    ],
    "акъудзавайди": [
        "take.out-IMPF-PST-SBST"
    ],
    "акъудна": [
        "let.us.out-AOR",
        "get.out-AOC",
        "take.out-AOC"
    ],
    "акьаз": [
        "hit-INF"
    ],
    "акьахна": [
        "jumping-AOC"
    ],
    "акьуллу": [
        "clever"
    ],
    "ала": [
        "is.there"
    ],
    "алад": [
        "exceed"
    ],
    "аладар": [
        "longed.ENT"
    ],
    "аладарда": [
        "longed.ENT-ENT"
    ],
    "алай": [
        "is.there-PST",
        "is.there-PTP",
        "is.there-AOP"
    ],
    "алатда": [
        "pass-ENT"
    ],
    "алатна": [
        "pass-AOC"
    ],
    "алатӀа": [
        "is.there-COND"
    ],
    "алдатмишарзава": [
        "deceive-PL-IMPF"
    ],
    "алифбарал": [
        "alphabets.to-OBL-SPSS"
    ],
    "алман": [
        "the.German"
    ],
    "алукӀна": [
        "wear.AOC-AOR"
    ],
    "алцурармир": [
        "decieved.ENT-PL-PROH"
    ],
    "алцурарна": [
        "deceiving.AOC",
        "decieved.ENT-PL-AOR"
    ],
    "ам": [
        "it",
        "that"
    ],
    "ама": [
        "still.be,.remain",
        "but",
        "he"
    ],
    "амай": [
        "he-AOP"
    ],
    "амайди": [
        "still.be,.remain-AOP-SBST",
        "he-PTP-SBST"
    ],
    "амайла": [
        "exist.doesn't-AOP-TEMP"
    ],
    "амалдив": [
        "with.slyness-OBL-ADESS"
    ],
    "амани": [
        "still.be,.remain-FOC",
        "he-FOC",
        "he-Q"
    ],
    "амач": [
        "be.in.CONT-NEG",
        "exist.doesn't",
        "still.be,.remain-NEG"
    ],
    "амачир": [
        "still.be,.remain-NEG.PST"
    ],
    "амаш": [
        "he-NEG"
    ],
    "амна": [
        "that.happing.AOC"
    ],
    "амни": [
        "those.and"
    ],
    "амукъда": [
        "will.stay-ENT"
    ],
    "амукъзава": [
        "stay-IMPF"
    ],
    "амукьин": [
        "remain-HORT"
    ],
    "ана": [
        "there"
    ],
    "анавай": [
        "there.from-PST"
    ],
    "анай": [
        "there-PST",
        "there-AOP"
    ],
    "анайни": [
        "there-PST-Q"
    ],
    "анал": [
        "that.on"
    ],
    "анариз": [
        "there-PL-DAT"
    ],
    "анжах": [
        "only"
    ],
    "аниз": [
        "there-DAT",
        "that-DAT"
    ],
    "анихъ": [
        "that-POESS"
    ],
    "анихъни": [
        "there.to-FOC"
    ],
    "анриз": [
        "there"
    ],
    "арабриз": [
        "arab-PL-OBL-DAT"
    ],
    "арада": [
        "among-INESS",
        "between-INESS"
    ],
    "арадай": [
        "among"
    ],
    "арадлай": [
        "a.while.after"
    ],
    "артух": [
        "better"
    ],
    "архаин": [
        "comfort"
    ],
    "асвальтдал": [
        "asphalt-INESS-SPSS"
    ],
    "атай": [
        "come-PTP",
        "coming-PST"
    ],
    "атайди": [
        "come-PST-SBST"
    ],
    "атайла": [
        "coming-PTP-TEMP"
    ],
    "атана": [
        "coming-AOR",
        "come-AOR",
        "come-AOC"
    ],
    "атана~агакьда": [
        "REACHED.ENT"
    ],
    "атанва": [
        "coming-PERF"
    ],
    "атун": [
        "come"
    ],
    "атӀуд": [
        "cut"
    ],
    "атӀуз": [
        "cut-INF"
    ],
    "ахвара": [
        "dream-INESS",
        "dream-ERG"
    ],
    "ахвариз": [
        "dream.in-ERG-DAT"
    ],
    "ахкуна": [
        "seing.AOC-AOR"
    ],
    "ахпа": [
        "After",
        "then"
    ],
    "ахпадаказ": [
        "then"
    ],
    "ахпадиказ": [
        "then"
    ],
    "ахъайда": [
        "open-PST-ENT",
        "released.ENT"
    ],
    "ахъайзава": [
        "open-IMPF"
    ],
    "ахъайна": [
        "open-AOR"
    ],
    "ахъатайдилай": [
        "appear.of-AOP-SBST-TEMP-PST"
    ],
    "ахъатзава": [
        "appereance-IMPF"
    ],
    "ахъая": [
        "send.away.IMPV"
    ],
    "ахьтин": [
        "like.that"
    ],
    "ацакьна": [
        "sit-AOR"
    ],
    "ацукьарда": [
        "seat.ENT"
    ],
    "ацукьарна": [
        "boarding.AOC"
    ],
    "ацукьда": [
        "sitting.down.AOC-ENT"
    ],
    "ашар": [
        "plov-PL"
    ],
    "ашкъидикай": [
        "love-ERG-SBSS-EL",
        "love-ERG-SBSS-ERG-INELAT"
    ],
    "ашукь": [
        "ashuq"
    ],
    "ашукьди": [
        "ashuq-DIR",
        "ashuq-ERG"
    ],
    "ашукьдиз": [
        "ashuq-ERG-DAT",
        "ashuq-DIR-DAT"
    ],
    "ая": [
        "do"
    ],
    "аял": [
        "child"
    ],
    "аялар": [
        "child-PL"
    ],
    "аялари": [
        "child-PL-ERG"
    ],
    "аяларихъ": [
        "child-PL-OBL-POESS"
    ],
    "аялдин": [
        "child-OBL-GEN"
    ],
    "аяр": [
        "nice"
    ],
    "багъишламишзава": [
        "present-IMPF"
    ],
    "багъишна": [
        "present-AOR"
    ],
    "баде": [
        "grandmother"
    ],
    "бала": [
        "baby"
    ],
    "балаяр": [
        "baby-PL"
    ],
    "балкӀан": [
        "horse"
    ],
    "балкӀандал": [
        "horse-OBL-SPSS",
        "horse-SPSS"
    ],
    "балкӀанди": [
        "horse-ERG"
    ],
    "балкӀандин": [
        "horse-ERG-GEN"
    ],
    "балкӀандини": [
        "horse-ERG-FOC"
    ],
    "бахтавар": [
        "happy"
    ],
    "башламишда": [
        "started.ENT",
        "started.ENT-INESS"
    ],
    "башламишзава": [
        "started.ENT-IMPF"
    ],
    "башламишна": [
        "started-AOR"
    ],
    "беес": [
        "but"
    ],
    "белке": [
        "maybe"
    ],
    "бере": [
        "time"
    ],
    "береда": [
        "time-INESS",
        "time-ENT"
    ],
    "бес": [
        "but"
    ],
    "бина": [
        "building"
    ],
    "боеприпас": [
        "ammunition"
    ],
    "больницадиз": [
        "hospital-ERG-DAT"
    ],
    "буба": [
        "father"
    ],
    "бубади": [
        "grandfather-DIR",
        "father-ERG",
        "grandfather-ERG"
    ],
    "бубадизни": [
        "father-OBL-DAT-FOC"
    ],
    "бубадин": [
        "grandfather-DIR-GEN"
    ],
    "бубадини": [
        "grandfather-DIR-FOC"
    ],
    "бубадихъ": [
        "father-OBL-POESS"
    ],
    "булахдал": [
        "spring-INESS-SPSS"
    ],
    "булахдин": [
        "spring-DIR-GEN"
    ],
    "бурулгъан": [
        "whirlpool"
    ],
    "ва": [
        "and"
    ],
    "вав": [
        "2sg-AD"
    ],
    "вад": [
        "five"
    ],
    "ваз": [
        "2sg-DAT",
        "you"
    ],
    "вак": [
        "pig"
    ],
    "вакай": [
        "2sg-SBSS-EL"
    ],
    "вакар": [
        "pig-PL"
    ],
    "вал": [
        "for.you"
    ],
    "ван": [
        "voice"
    ],
    "ван~хьанач": [
        "LISTEN-NEG"
    ],
    "варз": [
        "moon"
    ],
    "вах": [
        "sister"
    ],
    "вахвални": [
        "sister-PL-FOC"
    ],
    "вахгана": [
        "return-AOR"
    ],
    "вахкана": [
        "give-AOR"
    ],
    "вахкуда": [
        "return-FUT"
    ],
    "вахт": [
        "time"
    ],
    "вахтара": [
        "time-PL-ERG"
    ],
    "вахтинда": [
        "time-ERG-GEN-INESS"
    ],
    "вахча": [
        "give"
    ],
    "вахъ": [
        "2sg-POESS"
    ],
    "вацра": [
        "month.in-ERG"
    ],
    "вач": [
        "go.IMPV"
    ],
    "ваъ": [
        "no"
    ],
    "вегьена": [
        "threw-AOC",
        "threw-AOR"
    ],
    "вегьиз": [
        "threw-IMC"
    ],
    "везирриз": [
        "viziers-ERG-DAT"
    ],
    "векьер": [
        "hay-PL"
    ],
    "векьиз": [
        "hay-ERG-DAT"
    ],
    "верци": [
        "sweet"
    ],
    "вефасуз": [
        "untrusted"
    ],
    "ви": [
        "2sg.gen"
    ],
    "вил": [
        "eye"
    ],
    "вилаятда": [
        "province.in-INESS"
    ],
    "вилаятдиз": [
        "province.in-DIR-DAT",
        "province.in-ERG-DAT"
    ],
    "вилаятдин": [
        "country.in-DIR-GEN"
    ],
    "вилер": [
        "eye-PL"
    ],
    "вили": [
        "blue"
    ],
    "вилик": [
        "before"
    ],
    "виликай": [
        "eye-OBL-SUB-EL"
    ],
    "вине": [
        "over"
    ],
    "винел": [
        "on"
    ],
    "винелай": [
        "over-SPSS-INELAT"
    ],
    "виняй": [
        "height.from-PST"
    ],
    "вири": [
        "all"
    ],
    "виридаз": [
        "Everything-INESS-DAT"
    ],
    "вирини": [
        "Everything-FOC"
    ],
    "вич": [
        "himself",
        "2sg.gen-NEG"
    ],
    "вичал": [
        "himself-ERG-SPSS",
        "on.itself"
    ],
    "вичелай": [
        "himself-INESS-SPSS-AOP"
    ],
    "вичи": [
        "himself-ERG"
    ],
    "вичивай": [
        "himself-OBL-AD-EL"
    ],
    "вичиз": [
        "himself-ERG-DAT"
    ],
    "вичикай": [
        "himself-ERG-SBSS-EL"
    ],
    "вичин": [
        "himself-OBL-GEN",
        "himself-ERG-GEN",
        "her"
    ],
    "военный": [
        "military"
    ],
    "вун": [
        "2sg.abs"
    ],
    "вуна": [
        "2sg.abs-ERG",
        "2sg.erg"
    ],
    "вутӀ": [
        "where"
    ],
    "вутӀнатӀани": [
        "where-AOC-COND-FOC"
    ],
    "вуч": [
        "what"
    ],
    "вучиз": [
        "what-ERG-DAT"
    ],
    "вучин": [
        "what-ERG-GEN"
    ],
    "вуш": [
        "what"
    ],
    "вушда": [
        "what-ENT"
    ],
    "высоковольтный": [
        "high.voltage"
    ],
    "гагьатзава": [
        "escape-IMPF",
        "escaped-IMPF"
    ],
    "гагьатна": [
        "escaped-AOR",
        "escape-AOR"
    ],
    "гада": [
        "boy"
    ],
    "гадади": [
        "boy-ERG"
    ],
    "гададив": [
        "boy-DIR-AD"
    ],
    "гададивай": [
        "guy.from"
    ],
    "гададиз": [
        "boy-DIR-DAT"
    ],
    "гададизни": [
        "boy-ERG-DAT-FOC"
    ],
    "гададин": [
        "boy-DIR-GEN"
    ],
    "гададини": [
        "boy-DIR-GEN-ERG"
    ],
    "гадайри": [
        "boys"
    ],
    "гадан": [
        "boy-GEN"
    ],
    "гадани": [
        "boy-FOC",
        "boy-Q"
    ],
    "гадар": [
        "threw"
    ],
    "газет": [
        "newspaper"
    ],
    "газетдани": [
        "newspaper-INESS-FOC"
    ],
    "газетдиз": [
        "newspaper-OBL-DAT"
    ],
    "газетдин": [
        "newspaper-OBL-GEN"
    ],
    "гайдалай": [
        "give-PST-ENT-SPSS-AOP"
    ],
    "гайи": [
        "give-AOP"
    ],
    "галаз": [
        "with",
        "with-DAT"
    ],
    "галазни": [
        "with-FOC"
    ],
    "галай": [
        "was",
        "with-PST"
    ],
    "галатна": [
        "tire-AOR"
    ],
    "галатнавай": [
        "tire-PERF-PTP"
    ],
    "галатнавайди": [
        "tire-PERF-PTP-SBST"
    ],
    "галукь": [
        "hit"
    ],
    "гана": [
        "give-AOR",
        "give-AOC",
        "giving.AOC"
    ],
    "ганач": [
        "give-AOC-NEG"
    ],
    "ганва": [
        "give-PERF"
    ],
    "ганвай": [
        "give-PST"
    ],
    "гатаз": [
        "beat-INF"
    ],
    "гатана": [
        "knock-AOC"
    ],
    "гатдин": [
        "escape-SBST-MSD"
    ],
    "гатна": [
        "escape-AOR"
    ],
    "гатфар": [
        "spring"
    ],
    "гаф": [
        "word"
    ],
    "гафар": [
        "words",
        "word-PL"
    ],
    "гафарда": [
        "talking-FUT"
    ],
    "гафарзава": [
        "talking-IMPF"
    ],
    "гафариз~аламукьнава": [
        "STAYED.TALKING"
    ],
    "гафарна": [
        "talking-AOC"
    ],
    "гафни": [
        "word-FOC"
    ],
    "гвадардай": [
        "throwing.AOC-ENT-AOP"
    ],
    "гваз": [
        "with",
        "have-DAT"
    ],
    "гвай": [
        "was"
    ],
    "гевгьерар": [
        "pearls-PL"
    ],
    "гевгьеррин": [
        "pearls-ERG-GEN"
    ],
    "гейчек": [
        "beautiful"
    ],
    "гелерихъ": [
        "footprint.to-POESS"
    ],
    "гелкъвена": [
        "looked.for-AOR"
    ],
    "гзаф": [
        "a.lot"
    ],
    "гила": [
        "now"
    ],
    "гила-": [
        "now"
    ],
    "градус": [
        "degree"
    ],
    "границадиз": [
        "border-DIR-DAT"
    ],
    "гуда": [
        "give-ENT",
        "give-FUT",
        "to.give-FUT"
    ],
    "гудайвал": [
        "give.will-ENT-AOP-PURP"
    ],
    "гудий~вал": [
        "TO.GIVE"
    ],
    "гуз": [
        "give.will-DAT",
        "to.give-INF",
        "give-IMC",
        "give.will-IMC"
    ],
    "гузва": [
        "to.give-IMPF",
        "give-IMPF"
    ],
    "гум": [
        "smoke"
    ],
    "гумир": [
        "export"
    ],
    "гун": [
        "give.HORT",
        "to.give"
    ],
    "гуникай": [
        "giving-SBSS-AOP"
    ],
    "гутунна": [
        "attaching-AOC"
    ],
    "гуьгъуьна": [
        "behind"
    ],
    "гуьзлемишзава": [
        "wait-IMPF"
    ],
    "гуьре": [
        "for"
    ],
    "гуьрметарна": [
        "respect.do-PL-AOR"
    ],
    "гъавурда~акьуна": [
        "UNDERSTAND.AOR-AOR",
        "UNDERSTAND.AOR"
    ],
    "гъалиб": [
        "victorious"
    ],
    "гъана": [
        "bring-AOR",
        "brought.AOR-AOR"
    ],
    "гъанвай": [
        "brought.AOR-PERF-PST"
    ],
    "гъваш": [
        "bring.IMPV",
        "bring?"
    ],
    "гъвечи": [
        "small"
    ],
    "гъвечӀи": [
        "small"
    ],
    "гъел": [
        "plough"
    ],
    "гъелни": [
        "plough-FOC"
    ],
    "гъида": [
        "will.bring-ENT"
    ],
    "гъиз": [
        "bring.IMC",
        "will.bring-DAT"
    ],
    "гъил": [
        "hand"
    ],
    "гъиле": [
        "hand-INESS"
    ],
    "гъилеваз": [
        "hand-OBL-DAT"
    ],
    "гъилерив": [
        "hand-PL-ERG-AD"
    ],
    "гъиляй": [
        "arm.from",
        "hand-EL"
    ],
    "гъин": [
        "bring.HORT",
        "will.bring-HORT"
    ],
    "гъишни": [
        "bring.IMPV.Q-FOC"
    ],
    "гъуьлуьн": [
        "sea-ERG-GEN"
    ],
    "гьа": [
        "that,.the.same",
        "today"
    ],
    "гьа~береда": [
        "AT.THAT.TIME-INESS"
    ],
    "гьабур": [
        "them"
    ],
    "гьабури": [
        "them-ERG"
    ],
    "гьабуризни": [
        "them-ERG-DAT-FOC"
    ],
    "гьабурилай": [
        "them-ERG-TEMP-AOP"
    ],
    "гьабурни": [
        "them-FOC"
    ],
    "гьабурун": [
        "them-ERG-GEN"
    ],
    "гьава": [
        "weather"
    ],
    "гьада": [
        "she"
    ],
    "гьадаз": [
        "she-DAT",
        "that,.the.same-ERG-DAT"
    ],
    "гьадан": [
        "that,.the.same-OBL-GEN"
    ],
    "гьадисени": [
        "happening-Q"
    ],
    "гьазим": [
        "lot.of"
    ],
    "гьайван": [
        "animal"
    ],
    "гьайванарин": [
        "animal-PL-ERG-GEN"
    ],
    "гьакӀ": [
        "just"
    ],
    "гьакӀа": [
        "just-ERG"
    ],
    "гьаларикай": [
        "solution-PL-ERG-SBSS-EL"
    ],
    "гьалда": [
        "solution-INESS"
    ],
    "гьам": [
        "that"
    ],
    "гьамамдиз": [
        "bathhouse.in?-DIR-DAT"
    ],
    "гьана": [
        "today-AOR",
        "there"
    ],
    "гьанай": [
        "that-INELAT"
    ],
    "гьанал": [
        "that-OBL-SPSS",
        "there-SPSS"
    ],
    "гьаниз": [
        "there",
        "that-ERG-DAT"
    ],
    "гьанузди": [
        "there-DIR"
    ],
    "гьар": [
        "every"
    ],
    "гьарад": [
        "everybody"
    ],
    "гьарайзу": [
        "screaming-UNK"
    ],
    "гьатда": [
        "enter.FUT-FUT"
    ],
    "гьатна": [
        "enter-AOC",
        "enter.FUT-AOR",
        "enter-AOR"
    ],
    "гьатнава": [
        "enter-PERF"
    ],
    "гьафте": [
        "week"
    ],
    "гьафтеда": [
        "week-INESS"
    ],
    "гьахна": [
        "enter-AOR"
    ],
    "гьахнава": [
        "enter-PERF"
    ],
    "гьахьин": [
        "enter-HORT"
    ],
    "гьахьтай": [
        "enter-AOP"
    ],
    "гьахьтин": [
        "enter-OBL-GEN"
    ],
    "гьаятдиз": [
        "life-OBL-DAT"
    ],
    "гьаятдилай": [
        "life.from-SBST-SPSS-AOP"
    ],
    "гьаятдин": [
        "life-OBL-GEN"
    ],
    "гьейетдай": [
        "yard.in-INELAT"
    ],
    "гьейетдал": [
        "yard.in-INESS-SPSS"
    ],
    "гьелбетда": [
        "Of.course-INESS"
    ],
    "гьефте": [
        "week"
    ],
    "гьефтедлай": [
        "week-ERG-TEMP-INELAT"
    ],
    "гьи": [
        "this"
    ],
    "гьижран": [
        "separation"
    ],
    "гьизяхъине": [
        "now"
    ],
    "гьикӀ": [
        "how"
    ],
    "гьимаенда": [
        "brought.up-INESS"
    ],
    "гьимаенда~йашамиш": [
        "BROUGHT.UP"
    ],
    "гьин": [
        "which"
    ],
    "гьина": [
        "where"
    ],
    "гьинай": [
        "which-INELAT"
    ],
    "гьинал": [
        "where-SPSS"
    ],
    "гьиниз": [
        "where.to",
        "where"
    ],
    "гьисабзава": [
        "count-IMPF"
    ],
    "гьич": [
        "never"
    ],
    "гьужумна": [
        "attack-AOR"
    ],
    "гьунар": [
        "courage"
    ],
    "гьундуьрда": [
        "high"
    ],
    "гьутӀанал": [
        "that.yonder-SPSS"
    ],
    "гьуьлун": [
        "sea-ERG-GEN"
    ],
    "гьуьлуьз": [
        "sea-ERG-DAT"
    ],
    "гьуьлуьн": [
        "sea-OBL-GEN"
    ],
    "гьым": [
        "Uhm"
    ],
    "дагъ": [
        "mountain"
    ],
    "дагъви": [
        "mountain.person"
    ],
    "дагъвийриз": [
        "mountain.person-PL-ERG-DAT"
    ],
    "дагъларилай": [
        "mountain-SPSS-PL-ERG-SPSS-EL"
    ],
    "дагъустанвидин": [
        "dagistanish-ERG-GEN"
    ],
    "дагьи": [
        "great"
    ],
    "дастан": [
        "dastan"
    ],
    "дахадихъ": [
        "elder.brother-OBL-POESS"
    ],
    "девирда": [
        "time-INESS"
    ],
    "девлет": [
        "country"
    ],
    "девлетари": [
        "country-PL-ERG"
    ],
    "дегьшет": [
        "disaster"
    ],
    "дежурнидини": [
        "on.duty-DIR-FOC"
    ],
    "дежурный": [
        "on..duty"
    ],
    "дежурныйдиз": [
        "on..duty-ERG-DAT"
    ],
    "дейесен": [
        "it.seems"
    ],
    "дели": [
        "mad"
    ],
    "дердинай": [
        "grief-ERG-GEN-EL"
    ],
    "дередин": [
        "valley-OBL-GEN"
    ],
    "дерт": [
        "grief"
    ],
    "десте": [
        "group"
    ],
    "диване": [
        "lovesick"
    ],
    "диде": [
        "mother"
    ],
    "дидевални": [
        "mother-PL-FOC"
    ],
    "дидеди": [
        "mother-ERG"
    ],
    "дидедиз": [
        "mother-DIR-DAT",
        "mother-OBL-DAT"
    ],
    "дидедин": [
        "mother-DIR-GEN",
        "mother-OBL-GEN",
        "mother-ERG-GEN"
    ],
    "дидедихъ": [
        "mother-OBL-POESS"
    ],
    "дидени": [
        "mother-FOC"
    ],
    "дили": [
        "language"
    ],
    "динжарна": [
        "will.have.a.rest-PL-AOR"
    ],
    "динжвалда": [
        "will.have.a.rest-PURP-FUT"
    ],
    "дишегьлиярни": [
        "women.also-PL-FOC"
    ],
    "документар": [
        "document-PL"
    ],
    "докъккъуздиз": [
        "9-DIR-DAT"
    ],
    "докъкъузюз": [
        "nine.hundred"
    ],
    "дуст": [
        "friend"
    ],
    "дуствал": [
        "friendship"
    ],
    "дустини": [
        "friend-ERG-FOC"
    ],
    "дустиниз": [
        "friend-HORT-ERG-DAT"
    ],
    "дуьз": [
        "great"
    ],
    "дуьздик": [
        "right-DIR-SBSS"
    ],
    "дуьзмуьшайди": [
        "endure-AOP-DIR"
    ],
    "еврей": [
        "jewish"
    ],
    "егьена": [
        "is.putting-AOR"
    ],
    "еке": [
        "great"
    ],
    "жаваб": [
        "answer"
    ],
    "жаван": [
        "young"
    ],
    "жагъурда": [
        "find-ENT"
    ],
    "жагъурна": [
        "find-AOR"
    ],
    "жаза": [
        "punishment"
    ],
    "жамаатдин": [
        "people-DIR-GEN"
    ],
    "жанавурри": [
        "wolk-ERG"
    ],
    "жеда": [
        "be-ENT",
        "be-INESS",
        "be-FUT",
        "became.ENT",
        "was.ENT"
    ],
    "жеда~чавай": [
        "be-FUT-TO.US-EL"
    ],
    "жедай": [
        "be-FUT-PTP"
    ],
    "жедайвалди": [
        "be-FUT-PST-IMMANT"
    ],
    "жедайди": [
        "be-FUT-PTP-SBST"
    ],
    "жедач": [
        "can-NEG"
    ],
    "жедашни": [
        "can-NEG-FOC"
    ],
    "жедиш": [
        "be-SBST-NEG"
    ],
    "жезва": [
        "be-IMPF"
    ],
    "жезвай": [
        "being-IMPF-PST"
    ],
    "жезвайди": [
        "be-IMPF-PTP-DIR"
    ],
    "жезвач": [
        "be-IMPF-NEG"
    ],
    "жезвачир": [
        "be-IMPF-NEG.PST"
    ],
    "желб": [
        "attract"
    ],
    "жемир": [
        "don't.be-PROH"
    ],
    "жемят": [
        "public"
    ],
    "жемятдиз": [
        "people.to"
    ],
    "жен": [
        "being"
    ],
    "жени": [
        "be.FUT.Q"
    ],
    "жервал": [
        "will.be"
    ],
    "жи": [
        "our"
    ],
    "жив": [
        "snow"
    ],
    "жигъирарни": [
        "paths-PL-FOC"
    ],
    "жув": [
        "us"
    ],
    "жува": [
        "us-ERG"
    ],
    "жуваз": [
        "us-ERG-DAT",
        "yourself-DAT"
    ],
    "жувазни": [
        "us-ERG-DAT-FOC"
    ],
    "жуван": [
        "us-OBL-GEN"
    ],
    "жугваз": [
        "to.suffer-INF"
    ],
    "жузун": [
        "ask"
    ],
    "жумледен": [
        "Too"
    ],
    "жуьре": [
        "kind"
    ],
    "жуьт": [
        "pair"
    ],
    "за": [
        "1sg.ERG"
    ],
    "завай": [
        "1sg.ERG-AD-EL"
    ],
    "заз": [
        "1sg.ERG-DAT",
        "I-DAT"
    ],
    "зазни": [
        "1sg.ERG-DAT-FOC"
    ],
    "зайиф": [
        "weak"
    ],
    "зал": [
        "1sg.ERG-SPSS"
    ],
    "залай": [
        "1sg.ERG-SPSS-EL"
    ],
    "залан": [
        "heavy"
    ],
    "зани": [
        "1sg.ERG-FOC"
    ],
    "запрос": [
        "demand"
    ],
    "застава": [
        "outpost"
    ],
    "заставадал": [
        "outpost-SPSS"
    ],
    "заставадилай": [
        "outpost-DIR-SPSS-EL"
    ],
    "заставал": [
        "outpost-SPSS"
    ],
    "затӀна": [
        "thing-AOR"
    ],
    "захъ": [
        "1sg.ERG-POESS"
    ],
    "звоникдал": [
        "ring.button-INESS-SPSS"
    ],
    "зейиф": [
        "weak"
    ],
    "земляк": [
        "fellow.countryman"
    ],
    "зенгна": [
        "call-AOR",
        "let.call-AOR"
    ],
    "зи": [
        "1sg.gen"
    ],
    "зид": [
        "my"
    ],
    "зу": [
        "my",
        "1sg.gen"
    ],
    "зун": [
        "1sg.abs"
    ],
    "зунни": [
        "1sg.abs-AND",
        "1sg.abs-Q",
        "1sg.abs-FOC"
    ],
    "зурзун": [
        "tremor"
    ],
    "и": [
        "this",
        "and"
    ],
    "ибре": [
        "exemplary"
    ],
    "ибретани": [
        "exemplary"
    ],
    "ибур": [
        "these",
        "this-ABS.PL"
    ],
    "ибуриз": [
        "these-OBL-DAT"
    ],
    "ибурин": [
        "these-ERG-GEN",
        "these-OBL-GEN",
        "this-ABS.PL-ERG-GEN"
    ],
    "ибурни": [
        "these-FOC",
        "They"
    ],
    "ибуру": [
        "They",
        "these-ERG"
    ],
    "ибурувай": [
        "these-OBL-AD-EL"
    ],
    "ибурун": [
        "these-ERG-GEN",
        "their"
    ],
    "ибуруни": [
        "They.and",
        "these-ERG-Q"
    ],
    "иви": [
        "blood"
    ],
    "ивиди": [
        "blood-ERG"
    ],
    "ивиз": [
        "night"
    ],
    "игила": [
        "now"
    ],
    "ида": [
        "her",
        "this-ERG"
    ],
    "идаз": [
        "he.also-DAT",
        "her-DAT",
        "be-DAT"
    ],
    "идакай": [
        "he.also-SBSS-EL"
    ],
    "идал": [
        "he.again-SPSS",
        "him.to-SPSS"
    ],
    "идан": [
        "his",
        "he.also-GEN"
    ],
    "идани": [
        "he.also-FOC"
    ],
    "иддихатиз": [
        "to.have.a.rest-INF"
    ],
    "иер": [
        "beautiful"
    ],
    "иесини": [
        "owner-FOC"
    ],
    "изагьатар": [
        "testomonies"
    ],
    "изатна": [
        "that.thing-AOR"
    ],
    "ийида": [
        "make-ENT"
    ],
    "ийидай": [
        "do-FUT-PST",
        "make-ENT-INELAT"
    ],
    "ийидаш": [
        "make-ENT-NEG"
    ],
    "ийиз": [
        "make-INF",
        "make-DAT"
    ],
    "ийизва": [
        "make-IMPF"
    ],
    "ийизваш": [
        "make-IMPF-NEG"
    ],
    "ийимир": [
        "make-PROH"
    ],
    "ийин": [
        "do-MSD",
        "make-HORT",
        "make-GEN"
    ],
    "икьван": [
        "so.much"
    ],
    "икьрар": [
        "decision-PL",
        "agreement-PL"
    ],
    "икӀ": [
        "like.this"
    ],
    "икӀа": [
        "like.this"
    ],
    "илисарда": [
        "hidden?-PL-ENT"
    ],
    "илисна": [
        "hidden-AOC"
    ],
    "им": [
        "she",
        "it",
        "this",
        "he",
        "this-ABS"
    ],
    "има": [
        "this.one",
        "this"
    ],
    "имидини": [
        "uncle-OBL-AND"
    ],
    "имини": [
        "uncle-AND"
    ],
    "имкан": [
        "chance"
    ],
    "имни": [
        "he.and"
    ],
    "ина": [
        "here"
    ],
    "инай": [
        "here-PST"
    ],
    "инал": [
        "here",
        "here-SPSS"
    ],
    "иналай": [
        "here-SPSS-AOP"
    ],
    "инани": [
        "here-FOC"
    ],
    "инанмиш": [
        "believe"
    ],
    "инара": [
        "here-ERG"
    ],
    "иниз": [
        "here-DAT"
    ],
    "иникъ": [
        "here.to"
    ],
    "инлай": [
        "from.here"
    ],
    "инсан": [
        "man"
    ],
    "инсанар": [
        "man-PL"
    ],
    "инсанди": [
        "man-ERG"
    ],
    "инсандихъ": [
        "man-ERG-POESS"
    ],
    "инсанрин": [
        "man-ERG-GEN"
    ],
    "истирагьатайдалай": [
        "rest.from-AOP-ENT-TEMP-PST"
    ],
    "историяр": [
        "story-PL"
    ],
    "истрагьетна": [
        "have.are.rest-AOR"
    ],
    "исяатни": [
        "now-FOC"
    ],
    "исятда": [
        "now-INESS"
    ],
    "итем": [
        "man"
    ],
    "итемдиз": [
        "man-DIR-DAT"
    ],
    "ихтилат": [
        "talk"
    ],
    "ихтилатда": [
        "talk-FUT"
    ],
    "ихьтин": [
        "such"
    ],
    "ичӀерна": [
        "pouring.AOC-AOR"
    ],
    "ичӀи": [
        "empty"
    ],
    "ишаре": [
        "sign"
    ],
    "иштиракна": [
        "participate-AOR"
    ],
    "йаймишна": [
        "spread-AOR"
    ],
    "йашамишзава": [
        "live-IMPF"
    ],
    "йикъуз": [
        "day.in"
    ],
    "йис": [
        "year"
    ],
    "йисар": [
        "year-PL"
    ],
    "йисиз": [
        "year-ERG-DAT"
    ],
    "йитар": [
        "waters-PL"
    ],
    "йиф": [
        "night"
    ],
    "йифен": [
        "night-OBL-GEN"
    ],
    "йифиз": [
        "night-OBL-DAT",
        "night-ERG-DAT"
    ],
    "кагъаз": [
        "paper"
    ],
    "казарма": [
        "barrack"
    ],
    "казармадал": [
        "barrack-INESS-SPSS"
    ],
    "кайла": [
        "burn-PTP-TEMP"
    ],
    "кам": [
        "step"
    ],
    "камни": [
        "step.also"
    ],
    "камуз": [
        "to.the.bottom"
    ],
    "кана": [
        "burn-AOR"
    ],
    "кани": [
        "dear-ERG"
    ],
    "канивилин": [
        "love-PURP-ERG-GEN",
        "dear-ERG-.NESS-ERG-GEN"
    ],
    "капашда": [
        "hadful-INESS"
    ],
    "капитан": [
        "captain"
    ],
    "кар": [
        "case"
    ],
    "кас": [
        "man"
    ],
    "касди": [
        "man-ERG"
    ],
    "касдиз": [
        "man-OBL-DAT"
    ],
    "кассетар": [
        "casset-PL"
    ],
    "кастин": [
        "man-OBL-GEN"
    ],
    "катда": [
        "ran.ENT"
    ],
    "катна": [
        "running-AOC"
    ],
    "каф": [
        "foam"
    ],
    "качалдивай": [
        "being.bald-DIR-AD-AOP"
    ],
    "кван": [
        "please.do"
    ],
    "квез": [
        "2pl.dat",
        "you.to-DAT"
    ],
    "квезни": [
        "2pl.dat-FOC"
    ],
    "квекай": [
        "from.ya'll-AOP"
    ],
    "кеф": [
        "mood"
    ],
    "ки": [
        "that"
    ],
    "киз": [
        "that-DAT"
    ],
    "киник": [
        "down"
    ],
    "кицӀ": [
        "dog"
    ],
    "кицӀиз": [
        "dog-ERG-DAT"
    ],
    "кицӀин": [
        "dog-ERG-GEN"
    ],
    "кицӀихъ": [
        "dog-ERG-POESS"
    ],
    "кичӀе": [
        "fear"
    ],
    "кишинзава": [
        "hungry.also-GEN-IMPF"
    ],
    "ккӀида": [
        "fight.FUT-ENT"
    ],
    "ковшда": [
        "mug?-INESS"
    ],
    "комиссоватна": [
        "commmissurate-AOR"
    ],
    "концерт": [
        "concert"
    ],
    "концертар": [
        "concert-PL"
    ],
    "крар": [
        "things"
    ],
    "ксана": [
        "sleep-AOR"
    ],
    "ксанвай": [
        "sleep-PERF-PTP"
    ],
    "ктаб": [
        "book"
    ],
    "ктабда": [
        "book-INESS"
    ],
    "ктадмир": [
        "touch.not.PROHIB-PROH"
    ],
    "ктӀан": [
        "beat"
    ],
    "кудна": [
        "hang.AOC-AOR"
    ],
    "кумазни": [
        "as.soon.as-FOC"
    ],
    "купча": [
        "bill.of.sale"
    ],
    "кутада": [
        "put.ENT-ENT"
    ],
    "кутуна": [
        "put-AOC"
    ],
    "кутунва": [
        "put-PERF"
    ],
    "кутӀур": [
        "create"
    ],
    "кутӀура": [
        "create"
    ],
    "кучукна": [
        "bury-AOR"
    ],
    "куь": [
        "your"
    ],
    "куьмек": [
        "help"
    ],
    "куьмекда": [
        "help-ENT"
    ],
    "куьмекдатӀа": [
        "help-ENT-COND"
    ],
    "куьн": [
        "2pl.abs"
    ],
    "куьне": [
        "you"
    ],
    "куьтни": [
        "not.a.word"
    ],
    "куьтягь": [
        "finish.MSD"
    ],
    "куьтях": [
        "finish"
    ],
    "куьтяхна": [
        "finished-AOC"
    ],
    "куьч": [
        "move"
    ],
    "кхьайтӀа": [
        "write-PST-COND"
    ],
    "кхьана": [
        "write-AOR"
    ],
    "кхьанва": [
        "write-PERF"
    ],
    "кхьидай": [
        "writing-ENT-AOP"
    ],
    "кхьин": [
        "to.write"
    ],
    "кхьихь": [
        "write"
    ],
    "кцӀизни": [
        "dog-ERG-DAT-FOC"
    ],
    "къабагъы": [
        "front"
    ],
    "къавумдини": [
        "relative-DIR-FOC"
    ],
    "къагъана": [
        "bring.again-AOR"
    ],
    "къаз": [
        "to.catch"
    ],
    "къакъатна": [
        "separate.AOR-AOR"
    ],
    "къакъудна": [
        "removing.AOC-AOR"
    ],
    "къалай": [
        "day.till-INELAT",
        "day.from"
    ],
    "къалди": [
        "day.till-DIR"
    ],
    "къалурзава": [
        "show-IMPF"
    ],
    "къалурзавач": [
        "show-IMPF-NEG"
    ],
    "къалурна": [
        "show-AOR",
        "show-AOC"
    ],
    "къанни": [
        "twenty"
    ],
    "къанни~вад": [
        "TWENTY.FIVE"
    ],
    "къапина": [
        "jar-ERG-AOR"
    ],
    "къарагъна": [
        "wake.up-AOR"
    ],
    "къари": [
        "old.woman"
    ],
    "къаткана": [
        "lie-AOC"
    ],
    "къатканава": [
        "lied-PERF",
        "lie-PERF"
    ],
    "къахчуна": [
        "take-AOR"
    ],
    "къачал": [
        "outdoors"
    ],
    "къачихъ": [
        "out"
    ],
    "къачу": [
        "take.IMPV",
        "take"
    ],
    "къачуда": [
        "take-FUT",
        "take-INESS"
    ],
    "къачуз": [
        "take-INF"
    ],
    "къачуна": [
        "take-AOC",
        "take-AOR"
    ],
    "къачурла": [
        "take.TEMP-TEMP",
        "take-TEMP"
    ],
    "къвазара": [
        "stop"
    ],
    "къвазна": [
        "stayed-AOR",
        "stopped.AOR-AOR"
    ],
    "къвазнава": [
        "stayed-PERF"
    ],
    "къвалахзава": [
        "working-IMPF"
    ],
    "къван": [
        "stone"
    ],
    "къвана": [
        "fell-AOR"
    ],
    "къванерин": [
        "stone-PL-OBL-GEN"
    ],
    "къвед": [
        "two"
    ],
    "къведа": [
        "come-ENT",
        "come-INESS",
        "come-FUT"
    ],
    "къведий": [
        "come-SBST-PST"
    ],
    "къвез": [
        "coming"
    ],
    "къвезва": [
        "come-IMPF"
    ],
    "къгъанава": [
        "buy-PERF"
    ],
    "къе": [
        "today"
    ],
    "къейд": [
        "celebrate"
    ],
    "къеле": [
        "fortress"
    ],
    "къеледив": [
        "fortress-OBL-AD"
    ],
    "къеледиз": [
        "fortress-OBL-DAT"
    ],
    "къен": [
        "inside"
    ],
    "къендер": [
        "sugarcube-PL"
    ],
    "къене": [
        "inside-INESS",
        "inside"
    ],
    "къенин": [
        "today-GEN-ERG-GEN"
    ],
    "къерардиз": [
        "decision-OBL-DAT",
        "decision-ERG-DAT"
    ],
    "къерехда": [
        "side-INESS"
    ],
    "къерехдив": [
        "bank-ERG-AD"
    ],
    "къерехдиз": [
        "bank-ERG-DAT"
    ],
    "къерехдилай": [
        "bank-DIR-SPSS-EL"
    ],
    "къери": [
        "more"
    ],
    "къетне": [
        "before"
    ],
    "къетнен": [
        "recently"
    ],
    "къизил": [
        "gold"
    ],
    "къиямат": [
        "amazing"
    ],
    "къугъванни": [
        "play-FOC"
    ],
    "къугьумдиз": [
        "relative-DIR-DAT"
    ],
    "къужахда": [
        "in.the.arms"
    ],
    "къужахтаваз": [
        "hand.in-OBL-DAT"
    ],
    "къула": [
        "fireplace.in",
        "fireplace-INESS"
    ],
    "къулаз": [
        "fireplace-OBL-DAT"
    ],
    "къулдурни": [
        "robbers-Q"
    ],
    "къулухъ": [
        "after"
    ],
    "къуна": [
        "took-AOR",
        "took",
        "take-AOR",
        "took-AOC"
    ],
    "къунва": [
        "took"
    ],
    "къунши": [
        "neighbor"
    ],
    "къуншияр": [
        "neighbor-PL"
    ],
    "къураз": [
        "pine-DAT"
    ],
    "къуру": [
        "dry"
    ],
    "къуш": [
        "bird"
    ],
    "къуьнел": [
        "shoulder-INESS-SPSS"
    ],
    "кьада": [
        "bought-INESS",
        "bought-ENT"
    ],
    "кьадар": [
        "enough"
    ],
    "кьадатӀа": [
        "take.FUT.COND"
    ],
    "кьатӀизва": [
        "see-IMPF"
    ],
    "кьван": [
        "so.much"
    ],
    "кьве": [
        "two"
    ],
    "кьвед": [
        "two"
    ],
    "кьведани": [
        "two-ERG-Q"
    ],
    "кьей": [
        "die"
    ],
    "кьейи": [
        "die.AOC-AOP"
    ],
    "кьена": [
        "died.AOC-AOC"
    ],
    "кьенва": [
        "died.AOC-PERF"
    ],
    "кьенвай": [
        "die-PERF-PST"
    ],
    "кьехе": [
        "neck"
    ],
    "кьил": [
        "head",
        "chapter"
    ],
    "кьилел": [
        "chapter-INESS-SPSS",
        "head-INESS-SPSS",
        "top.on"
    ],
    "кьилелни": [
        "chapter-ERG-SPSS-FOC"
    ],
    "кьилер": [
        "chapter-PL"
    ],
    "кьилерни": [
        "chapter-PL-FOC"
    ],
    "кьилиз": [
        "chapter-IMC"
    ],
    "кьилин": [
        "chapter-ERG-GEN"
    ],
    "кьилихъ": [
        "chapter-OBL-POESS"
    ],
    "кьилихъни": [
        "head-OBL-POESS-FOC"
    ],
    "кьилни": [
        "chapter-FOC"
    ],
    "кьиляй": [
        "chapter-EL"
    ],
    "кьимет": [
        "price"
    ],
    "кьиса": [
        "a.story"
    ],
    "кьисметда": [
        "fate-INESS"
    ],
    "кьуд": [
        "four"
    ],
    "кьулухъ": [
        "behind"
    ],
    "кьулухь": [
        "after"
    ],
    "кьуна": [
        "took-AOR",
        "took-AOC"
    ],
    "кьуьзуь": [
        "old"
    ],
    "кьуьл": [
        "kick"
    ],
    "кьуьлерна": [
        "dance-AOR"
    ],
    "кьуьруьдаказ": [
        "basically"
    ],
    "кюветдиз": [
        "ditch-DIR-DAT"
    ],
    "кӀадар": [
        "some"
    ],
    "кӀан": [
        "want"
    ],
    "кӀана": [
        "want-INESS"
    ],
    "кӀанда": [
        "want-FUT",
        "want-ENT",
        "want-INESS"
    ],
    "кӀандай": [
        "want-ENT-PST"
    ],
    "кӀандани": [
        "want-ENT-FOC"
    ],
    "кӀанзава": [
        "want-IMPF"
    ],
    "кӀанзавай": [
        "want-IMPF-PST",
        "want-IMPF-PTP"
    ],
    "кӀанзва": [
        "want-IMPF"
    ],
    "кӀани": [
        "want-ERG"
    ],
    "кӀаник": [
        "want-ERG-SBSS"
    ],
    "кӀантӀани": [
        "want.COND.FOC"
    ],
    "кӀануз": [
        "want-ERG-DAT",
        "botoom.at-ERG-DAT"
    ],
    "кӀарабни": [
        "bone-Q"
    ],
    "кӀарасар": [
        "wood-PL"
    ],
    "кӀарасарни": [
        "wood-PL-FOC"
    ],
    "кӀвала": [
        "house-INESS"
    ],
    "кӀвалара": [
        "house-PL-INESS"
    ],
    "кӀвалах": [
        "deed"
    ],
    "кӀвале": [
        "house-INESS",
        "room.at"
    ],
    "кӀвализ": [
        "house-OBL-DAT"
    ],
    "кӀватӀ": [
        "group"
    ],
    "кӀвач": [
        "leg"
    ],
    "кӀвачел": [
        "leg-INESS-SPSS"
    ],
    "кӀевиз": [
        "strong"
    ],
    "кӀевнавай": [
        "cover-PERF-PTP"
    ],
    "кӀелдин": [
        "read-SBST-HORT"
    ],
    "кӀукӀвал": [
        "top.on-OBL-SPSS"
    ],
    "кӀурцӀул": [
        "puppy"
    ],
    "кӀурцӀулар": [
        "puppy-PL"
    ],
    "кӀурцӀулди": [
        "puppy-DIR"
    ],
    "кӀурцӀулдиз": [
        "puppy-DIR-DAT"
    ],
    "кӀурцӀулдихъ": [
        "puppy-DIR-POESS"
    ],
    "кӀцарвияр": [
        "gusaris-PL"
    ],
    "лагердиз": [
        "camp-DIR-DAT"
    ],
    "лагь": [
        "say.IMP",
        "say"
    ],
    "лагьай": [
        "say-PST",
        "say-AOP"
    ],
    "лагьайвал": [
        "say-PST-PURP"
    ],
    "лагьайтӀа": [
        "say-PST-COND"
    ],
    "лагьана": [
        "say-AOC",
        "say-AOR",
        "say-ERG-AOR"
    ],
    "лагьанач": [
        "say-AOR-NEG"
    ],
    "лайих": [
        "worthy"
    ],
    "ламрал": [
        "donkey.on"
    ],
    "лап": [
        "very"
    ],
    "лезги": [
        "Lezgi"
    ],
    "лепеяр": [
        "waves-PL"
    ],
    "летний": [
        "summer"
    ],
    "линия": [
        "line"
    ],
    "лув~гана": [
        "FLEW-AOR"
    ],
    "лугьуда": [
        "say-ENT",
        "say-INESS",
        "said.ENT",
        "say-FUT"
    ],
    "лугьудай": [
        "say-FUT-PST",
        "say-ENT-AOP",
        "say-INESS-PST"
    ],
    "лугьуз": [
        "say-IMC",
        "say-DAT",
        "say-INF"
    ],
    "лугьузва": [
        "say-IMPF"
    ],
    "лугьузвай": [
        "say-IMPF-PST"
    ],
    "лугьун": [
        "say-MSD"
    ],
    "лугьурай": [
        "say-OPT"
    ],
    "луьквензава": [
        "grumbles-HORT-IMPF"
    ],
    "луьткведа": [
        "boat-INESS"
    ],
    "луьткведаваз": [
        "boat.in.being.IMC"
    ],
    "луьтквечидини": [
        "boatman-DIR-FOC"
    ],
    "луьтквечини": [
        "boatman-Q"
    ],
    "лянет": [
        "curse"
    ],
    "ма": [
        "you.know",
        "here.you.go"
    ],
    "магьалда": [
        "district-INESS"
    ],
    "мад": [
        "more"
    ],
    "мадни": [
        "more-FOC",
        "more-Q",
        "again"
    ],
    "мама": [
        "mother"
    ],
    "мамадиз": [
        "mother-OBL-DAT"
    ],
    "ман": [
        "you.know"
    ],
    "манат": [
        "manat.(azer)"
    ],
    "мани": [
        "song"
    ],
    "манийриз": [
        "song-PST-OBL-DAT"
    ],
    "маракьлы": [
        "interesting"
    ],
    "марф": [
        "rain"
    ],
    "маса": [
        "other"
    ],
    "масан": [
        "beauty"
    ],
    "массаж": [
        "massage"
    ],
    "махни": [
        "folk.tale"
    ],
    "машин": [
        "car"
    ],
    "машинар": [
        "car-PL"
    ],
    "машинара": [
        "car-PL-ERG"
    ],
    "межлис": [
        "event"
    ],
    "межлисда": [
        "even-INESS"
    ],
    "мез": [
        "tongue"
    ],
    "мейдандал": [
        "town.square-INESS-SPSS"
    ],
    "мейил": [
        "liking"
    ],
    "мелимди": [
        "teacher"
    ],
    "мертебели": [
        "floored"
    ],
    "месела": [
        "story"
    ],
    "меслегьетарна": [
        "decided-AOR"
    ],
    "меслятдив": [
        "advice.at-AD"
    ],
    "метлеб": [
        "wish"
    ],
    "метлебдин": [
        "wish-ERG-GEN"
    ],
    "метӀегъ": [
        "kind"
    ],
    "мехъерар": [
        "wedding-PL"
    ],
    "мехъерарда": [
        "wedding-PL-ENT"
    ],
    "мехъерарна": [
        "being.wed.AOC",
        "wedding-PL-AOR"
    ],
    "мехъерихъ": [
        "wedding-ERG-POESS"
    ],
    "миллет": [
        "nation"
    ],
    "мин": [
        "thousand"
    ],
    "мина": [
        "mine"
    ],
    "миннетдар": [
        "grateful"
    ],
    "мисал": [
        "example"
    ],
    "мици": [
        "another"
    ],
    "мицибур": [
        "others"
    ],
    "мицид": [
        "another"
    ],
    "мицида": [
        "another-ERG"
    ],
    "момент": [
        "moment"
    ],
    "мороз": [
        "frost"
    ],
    "муаллим": [
        "teacher"
    ],
    "муаллимди": [
        "teacher-ERG"
    ],
    "муаллимни": [
        "teacher-FOC"
    ],
    "мугьарибе": [
        "war"
    ],
    "мугьарибейра": [
        "war"
    ],
    "мугьубат": [
        "love"
    ],
    "мугьубатдикай": [
        "love-ERG-SBSS-EL"
    ],
    "мугьубатдин": [
        "love-ERG-GEN"
    ],
    "мукьвал": [
        "near"
    ],
    "мурад": [
        "wish"
    ],
    "муькуь": [
        "other.one"
    ],
    "муькуьбуруни": [
        "others.and-ERG-FOC"
    ],
    "муьстекъил": [
        "independent"
    ],
    "муьтлег": [
        "absolutely"
    ],
    "мягькем": [
        "strong"
    ],
    "на": [
        "you",
        "2sg.erg"
    ],
    "нагьахъ": [
        "in.vain"
    ],
    "накьв": [
        "soil"
    ],
    "накьвадикай": [
        "soil.from.under-DIR-SBSS-INELAT"
    ],
    "направление": [
        "direction.(rus)"
    ],
    "не": [
        "not"
    ],
    "не~исе": [
        "ANYWAY"
    ],
    "негъе": [
        "evening"
    ],
    "некедикай": [
        "milk-SBSS-EL"
    ],
    "немецариз": [
        "german-PL-ERG-DAT"
    ],
    "немецаринни": [
        "Germans-ERG-GEN-FOC"
    ],
    "немецарихъ": [
        "Germans-POESS"
    ],
    "немецди": [
        "german-DIR"
    ],
    "нефер": [
        "person"
    ],
    "нефес": [
        "breath"
    ],
    "ни": [
        "whoever"
    ],
    "ният": [
        "intention"
    ],
    "няни": [
        "evening"
    ],
    "нянихъди": [
        "evening-POESS-DIR"
    ],
    "обед": [
        "dinner"
    ],
    "оказывается": [
        "turned.out"
    ],
    "окруженияда": [
        "encirclement-INESS"
    ],
    "он": [
        "ten"
    ],
    "ондокъкъуздиз": [
        "nineteen.in-DIR-DAT"
    ],
    "отвечает": [
        "answers"
    ],
    "отпуска": [
        "vacation"
    ],
    "охрана": [
        "security-ERG"
    ],
    "паб": [
        "wife"
    ],
    "пад": [
        "side"
    ],
    "пакани": [
        "tomorrow-Q"
    ],
    "палкан": [
        "horse"
    ],
    "палкандивай": [
        "horse-OBL-AD-EL"
    ],
    "папаз": [
        "wife-ERG-DAT",
        "wife-DAT"
    ],
    "пара": [
        "very"
    ],
    "паркинай": [
        "park-ERG-GEN-AOP"
    ],
    "паркиниз": [
        "park-ERG-GEN-DAT"
    ],
    "паспорт": [
        "pasport"
    ],
    "патав": [
        "to",
        "side.on-AD"
    ],
    "патай": [
        "side"
    ],
    "патакай": [
        "for"
    ],
    "патал": [
        "side-OBL-SPSS",
        "for"
    ],
    "паталай": [
        "side.on-INELAT",
        "side.on-SPSS-ERG-INELAT",
        "side.on-SPSS-ERG-AOP"
    ],
    "патани": [
        "side.on-FOC"
    ],
    "патахъ": [
        "side.on-POESS",
        "side"
    ],
    "пачагь": [
        "king"
    ],
    "пачагьвализ": [
        "reign.to",
        "reigned.ENT-ERG-DAT"
    ],
    "пачагьдиз": [
        "king-DIR-DAT"
    ],
    "пачагьдизни": [
        "king-ERG-DAT-Q"
    ],
    "пачагьдин": [
        "king-DIR-GEN"
    ],
    "пачагьни": [
        "king-Q"
    ],
    "певицаярни": [
        "singers.also-PL-FOC"
    ],
    "пекер": [
        "clothes-PL",
        "clothes"
    ],
    "пекерни": [
        "clothes-FOC"
    ],
    "пекни": [
        "cloth"
    ],
    "пенжердай": [
        "window-INELAT"
    ],
    "пепе": [
        "bug"
    ],
    "пешком": [
        "on.foot"
    ],
    "пиларамаяр": [
        "saw.mills-PL"
    ],
    "пичинал": [
        "stove-OBL-SPSS"
    ],
    "плен": [
        "captivity(rus)"
    ],
    "по": [
        "on"
    ],
    "под": [
        "under"
    ],
    "призывник": [
        "conscript"
    ],
    "принцип": [
        "principle"
    ],
    "проверка": [
        "checking"
    ],
    "пуд": [
        "three"
    ],
    "пуда": [
        "three-ERG"
    ],
    "пул": [
        "money"
    ],
    "пӀузарар": [
        "lips-PL-PL"
    ],
    "пӀузаррал": [
        "lips-PL-INESS-SPSS"
    ],
    "рази": [
        "agree"
    ],
    "райондиз": [
        "coutryside.to-DIR-DAT"
    ],
    "ракъайтӀа": [
        "send.PTP.COND"
    ],
    "ракъуда": [
        "sent.ENT"
    ],
    "ракъузва": [
        "send-IMPF"
    ],
    "рахаз": [
        "speak.to-INF"
    ],
    "рахазва": [
        "speak-IMPF"
    ],
    "рахкана": [
        "give.back-AOR"
    ],
    "рахкуда": [
        "sent.ENT-ENT"
    ],
    "рахкъурнава": [
        "send-PERF"
    ],
    "регьет": [
        "easy"
    ],
    "регьметлу": [
        "dead"
    ],
    "рекъе": [
        "way,.road-INESS"
    ],
    "рекъел": [
        "way,.road-INESS-SPSS"
    ],
    "рекъелай": [
        "way,.road-INESS-SUPER-AOP"
    ],
    "рекъиз": [
        "way,.road-ERG-DAT"
    ],
    "рекье": [
        "way-INESS"
    ],
    "рекьер": [
        "way-PL"
    ],
    "рекьида": [
        "die-INESS",
        "die-FUT"
    ],
    "рекьиз": [
        "way-ERG-DAT"
    ],
    "республикайриз": [
        "countries-PL-ERG-DAT"
    ],
    "рессамдиз": [
        "artist-DIR-DAT"
    ],
    "ресторандиз": [
        "restaurant.to-OBL-DAT"
    ],
    "рехъ": [
        "road",
        "way"
    ],
    "рикӀ": [
        "heart"
    ],
    "рикӀал": [
        "heart-OBL-SPSS"
    ],
    "рикӀе": [
        "heart-INESS"
    ],
    "рикӀивайни": [
        "heart-ERG-AD-EL-FOC"
    ],
    "ругуд": [
        "six"
    ],
    "ругь": [
        "soul"
    ],
    "руказ": [
        "forest.to-OBL-DAT"
    ],
    "рукариз": [
        "forest.to-PL-ERG-DAT"
    ],
    "руш": [
        "girl"
    ],
    "руша": [
        "girl-ERG",
        "girl"
    ],
    "рушаз": [
        "girl-ERG-DAT",
        "girl-OBL-DAT"
    ],
    "рушан": [
        "girl-ERG-GEN"
    ],
    "рушар": [
        "girl-PL"
    ],
    "рушни": [
        "girl.and",
        "girl-FOC",
        "girl-Q"
    ],
    "са": [
        "one"
    ],
    "сабур": [
        "patience"
    ],
    "сагъ~хьурай": [
        "THANK.YOU"
    ],
    "сагъарна": [
        "heal.AOC-PL-AOR"
    ],
    "сагърай": [
        "heal.AOC-OPT"
    ],
    "сад": [
        "one"
    ],
    "сад~лагьана": [
        "SUDDENLY-AOR"
    ],
    "сада": [
        "one-ERG"
    ],
    "садни": [
        "one-FOC"
    ],
    "сакит": [
        "calm"
    ],
    "сакӀани": [
        "in.no.way-FOC",
        "in.no.way"
    ],
    "саламат": [
        "well"
    ],
    "санал": [
        "together"
    ],
    "сандрани": [
        "once-FOC"
    ],
    "саниз": [
        "because.of"
    ],
    "сарах": [
        "once"
    ],
    "саягъда": [
        "from.in-INESS"
    ],
    "свас": [
        "wife"
    ],
    "свасни": [
        "bride"
    ],
    "сев": [
        "bear"
    ],
    "сегьви": [
        "mistake"
    ],
    "сегьнеда": [
        "stage-INESS"
    ],
    "седакъетли": [
        "faithful"
    ],
    "семь": [
        "seven"
    ],
    "сергьедда": [
        "border.on-INESS"
    ],
    "сергьеддал": [
        "border.on-INESS-SPSS"
    ],
    "сеферни": [
        "time-FOC"
    ],
    "сивиз": [
        "mouth-ERG-DAT"
    ],
    "служитайди": [
        "had.been.serving-AOP-SBST"
    ],
    "служитна": [
        "served-AOR"
    ],
    "солдат": [
        "soldier"
    ],
    "солдатар": [
        "soldier-PL"
    ],
    "сонра": [
        "after"
    ],
    "стан": [
        "stati"
    ],
    "станция": [
        "station"
    ],
    "станциядал": [
        "station-INESS-SPSS"
    ],
    "станциядин": [
        "station-DIR-GEN"
    ],
    "стихотворение": [
        "poem"
    ],
    "стха": [
        "brother"
    ],
    "стхади": [
        "brother-ERG"
    ],
    "стхадивай": [
        "brother-OBL-AD-EL"
    ],
    "стхадизни": [
        "brother-ERG-DAT-FOC"
    ],
    "стхадихъ": [
        "brother-OBL-POESS"
    ],
    "стхани": [
        "brother-AND",
        "brother-FOC"
    ],
    "стхаяр": [
        "brother-PL"
    ],
    "суварилай": [
        "party's-OBL-SUPER-EL"
    ],
    "сура": [
        "after"
    ],
    "суьгьбетарна": [
        "talk-AOC"
    ],
    "суьгьбетда": [
        "talked-FUT"
    ],
    "сятдин": [
        "o'clock-ERG-GEN"
    ],
    "тавунвай": [
        "not.make.PRF.PTP-PERF-PST"
    ],
    "тавунмаз": [
        "don't.be"
    ],
    "тавур": [
        "not.make.PRF.PTP-AOP"
    ],
    "тавуртӀа": [
        "NEG.make.PTP-COND"
    ],
    "тагудай": [
        "NEG.giving.FUT.PTP-ENT-AOP"
    ],
    "тагьминан": [
        "approximately"
    ],
    "тада": [
        "put.ENT"
    ],
    "тазвайди": [
        "leave-IMPF-PTP-SBST"
    ],
    "тамамарна": [
        "finished-AOP-AOC"
    ],
    "тамаша": [
        "look.IMP"
    ],
    "тамашава": [
        "look"
    ],
    "тамашайтӀа": [
        "look.IMP-PST-COND"
    ],
    "тамашна": [
        "look.IMP-AOR"
    ],
    "тамир": [
        "leave-PROH"
    ],
    "таможня": [
        "custom.office"
    ],
    "тан": [
        "put.HORT"
    ],
    "тапарармир": [
        "lie-PROH"
    ],
    "тарафара": [
        "area-INESS"
    ],
    "тарифаради": [
        "praised-SBST"
    ],
    "тахтунал": [
        "throne.on"
    ],
    "тахурай": [
        "not.die-AOP"
    ],
    "тахьайтӀа": [
        "if.not.helps-COND",
        "could't-AOP-COND"
    ],
    "тахьана": [
        "could't-AOR"
    ],
    "тахьурай": [
        "can-PL-AOP",
        "can't-OPT"
    ],
    "телефон": [
        "phone"
    ],
    "терефдар": [
        "supporter"
    ],
    "териф": [
        "praise"
    ],
    "терсина": [
        "backwards",
        "on.the.contrary"
    ],
    "тийиз": [
        "don't-INF"
    ],
    "тике": [
        "piece"
    ],
    "тир": [
        "was"
    ],
    "той": [
        "wedding"
    ],
    "только": [
        "only"
    ],
    "туна": [
        "keep-AOC",
        "keep-AOR",
        "puting.AOC",
        "put-AOR"
    ],
    "тупӀаларни": [
        "ring-PL-FOC"
    ],
    "тур": [
        "put.IMPV"
    ],
    "тухвана": [
        "bringing.AOC-AOR",
        "bringing-AOC"
    ],
    "тухуда": [
        "take-ENT"
    ],
    "тухузвай": [
        "bringing-IMPF-PST",
        "take.FUT-IMPF-PST"
    ],
    "тухурла": [
        "when.taking.TEMP"
    ],
    "тучир": [
        "wasn't"
    ],
    "туш": [
        "cop.PST.NEG",
        "cop.NEG",
        "isn't"
    ],
    "туширни": [
        "cop.PST.NEG-Q"
    ],
    "туькӀуьрайла": [
        "created-AOP-TEMP"
    ],
    "туькӀуьрдай": [
        "creating.after-ENT-AOP"
    ],
    "туьтер": [
        "throat-PL"
    ],
    "тфенг": [
        "guns"
    ],
    "тфенгни": [
        "guns-FOC"
    ],
    "тфу": [
        "spit"
    ],
    "тхвана": [
        "take-AOR"
    ],
    "тӀа": [
        "if"
    ],
    "тӀарарда": [
        "secured-PL-ENT"
    ],
    "тӀва": [
        "other"
    ],
    "тӀвар": [
        "name"
    ],
    "тӀварни": [
        "name-Q",
        "name-FOC"
    ],
    "тӀварча": [
        "name.to"
    ],
    "тӀварчиз": [
        "name-ERG-DAT"
    ],
    "тӀимил": [
        "little"
    ],
    "тӀимил~кьван": [
        "A.LITTLE"
    ],
    "тӀун": [
        "do.it.IMPV"
    ],
    "тӀуьна": [
        "ate-AOC"
    ],
    "уже": [
        "already"
    ],
    "ун": [
        "yes"
    ],
    "учебкада": [
        "training.in-INESS"
    ],
    "уьлкведиз": [
        "country.to-DIR-DAT"
    ],
    "уьлуьхнавач": [
        "extinguish-PERF-NEG"
    ],
    "уьмурдин": [
        "life's-DIR-GEN"
    ],
    "уьчуьн": [
        "for"
    ],
    "уюнар": [
        "gym-PL"
    ],
    "фад": [
        "quickly"
    ],
    "фей": [
        "go-PST"
    ],
    "фейдалай": [
        "go-PST-ENT-TEMP-AOP"
    ],
    "фейила": [
        "go-AOP-TEMP"
    ],
    "фейитӀа": [
        "going.PTP.COND"
    ],
    "фейла": [
        "go-PST-TEMP"
    ],
    "фена": [
        "go-AOR",
        "go-AOC",
        "to.go-AOR"
    ],
    "фенава": [
        "go-PERF"
    ],
    "фенавай": [
        "go-PERF-PTP"
    ],
    "фенай": [
        "go-AOR-PTP"
    ],
    "фенва": [
        "go-PERF"
    ],
    "фенвач": [
        "go-PERF-NEG"
    ],
    "фендигарвилелди": [
        "by.cunning-PL-OBL-SUPER-DIR"
    ],
    "фида": [
        "go-ENT",
        "go-INESS",
        "go-FUT"
    ],
    "фидамаз": [
        "go-FUT-IMMANT",
        "go-ENT-IMMANT"
    ],
    "физ": [
        "go-INF",
        "go-DAT"
    ],
    "физава": [
        "go.out-IMPF"
    ],
    "физавай": [
        "going.is-IMPF-PST"
    ],
    "физва": [
        "go-IMPF"
    ],
    "фикир": [
        "thought"
    ],
    "фикирайдалай": [
        "a.thinking.MSD.off"
    ],
    "фикирарзава": [
        "attention-PL-IMPF"
    ],
    "фикирарни": [
        "attention-PL-Q"
    ],
    "фикирда": [
        "attention-ENT"
    ],
    "фикирдай": [
        "attention-ENT-AOP"
    ],
    "фикирдиз": [
        "attention-DIR-DAT"
    ],
    "фикирна": [
        "thing-AOR"
    ],
    "философия": [
        "philosopy"
    ],
    "фин": [
        "go-MSD",
        "go-GEN"
    ],
    "фу": [
        "bread"
    ],
    "фуни": [
        "bread-FOC",
        "bread-AND"
    ],
    "фургъунни": [
        "cart-FOC"
    ],
    "ха": [
        "ha"
    ],
    "хабар": [
        "news"
    ],
    "хала": [
        "aunt"
    ],
    "халади": [
        "aunt-ERG"
    ],
    "халкьарни": [
        "people.to.also-PL-FOC"
    ],
    "халкьдизни": [
        "people.to.also-ERG-DAT-Q"
    ],
    "халу": [
        "uncle"
    ],
    "хам": [
        "leather"
    ],
    "хан": [
        "break"
    ],
    "хана": [
        "be-AOR"
    ],
    "ханум": [
        "Ma'am"
    ],
    "ханума": [
        "Ma'am-ERG"
    ],
    "харадал": [
        "pile-OBL-SPSS"
    ],
    "характер": [
        "character"
    ],
    "хата": [
        "mistake"
    ],
    "хва": [
        "son"
    ],
    "хванахво": [
        "friend"
    ],
    "хвена": [
        "kept-AOR",
        "kept-AOC"
    ],
    "хвеши": [
        "happy"
    ],
    "хвешивиливай": [
        "happy-PL-OBL-AD-EL"
    ],
    "хгана": [
        "sent-AOR"
    ],
    "хейлаг": [
        "a.lot"
    ],
    "хер": [
        "wound"
    ],
    "хипер": [
        "sheep"
    ],
    "хиялдай": [
        "dream-INESS-PST"
    ],
    "хкадар": [
        "jumps"
    ],
    "хкадарда": [
        "jumps-ENT"
    ],
    "хкадарзава": [
        "jumps-IMPF"
    ],
    "хкаж": [
        "up"
    ],
    "хкаждий": [
        "up-SBST-PST"
    ],
    "хкатин": [
        "leave-HORT"
    ],
    "хкведа": [
        "return-ENT"
    ],
    "хкведай": [
        "return-INESS-AOP"
    ],
    "хкверла": [
        "return-PL-TEMP"
    ],
    "хкезва": [
        "returnes-IMPF"
    ],
    "хкягъа": [
        "choose.IMP"
    ],
    "хкягъда": [
        "choose.IMP-ENT"
    ],
    "хпер": [
        "sheep"
    ],
    "хтайла": [
        "return-PST-TEMP"
    ],
    "хтана": [
        "return-AOR",
        "return-AOC"
    ],
    "хтанава": [
        "return-PERF"
    ],
    "хтанва": [
        "return-PERF"
    ],
    "хтулни": [
        "grandchild-FOC"
    ],
    "хур": [
        "village"
    ],
    "хутах": [
        "take.back"
    ],
    "хуш": [
        "pleasant"
    ],
    "хуьда": [
        "defend-FUT"
    ],
    "хуьз": [
        "defend-INF",
        "to.keep-DAT"
    ],
    "хуьр": [
        "village"
    ],
    "хуьре": [
        "village-INESS"
    ],
    "хуьрей": [
        "village.out.of"
    ],
    "хуьруз": [
        "village-ERG-DAT"
    ],
    "хуьруьз": [
        "village.to-DAT",
        "village-OBL-DAT"
    ],
    "хуьруьн": [
        "village-ERG-GEN",
        "village.in-OBL-GEN"
    ],
    "хуьряй": [
        "village-INELAT",
        "village.in-INELAT"
    ],
    "хъайа": [
        "be"
    ],
    "хъая": [
        "be"
    ],
    "хъваз": [
        "drink-INF"
    ],
    "хъван": [
        "drink.HORT"
    ],
    "хъвана": [
        "drink-AOR"
    ],
    "хъвач": [
        "drink-NEG"
    ],
    "хъел": [
        "anger"
    ],
    "хъийида": [
        "did.again.ENT-INESS"
    ],
    "хъийидай": [
        "did.again.ENT-ENT-AOP"
    ],
    "хъийиз": [
        "did.again.ENT-DAT"
    ],
    "хъсан": [
        "good"
    ],
    "хъсанвилер": [
        "good-.NESS-PL"
    ],
    "хъсандик": [
        "good-OBL-SBSS"
    ],
    "хъфейдалай": [
        "go-PST-FUT-TEMP-PST"
    ],
    "хъфелахъди": [
        "go-TEMP-POESS-DIR"
    ],
    "хъфена": [
        "go-AOR",
        "returned-AOR",
        "go-AOC"
    ],
    "хъфенвач": [
        "go-PERF-NEG"
    ],
    "хъфизва": [
        "go.IMPF",
        "leave.FUT-IMPF"
    ],
    "хъфин": [
        "go.back.HORT"
    ],
    "хьай": [
        "happened-PTP"
    ],
    "хьайи": [
        "be-AOP"
    ],
    "хьайидалай": [
        "happened-AOP-FUT-TEMP-PST"
    ],
    "хьайиди": [
        "happened-AOP-SBST"
    ],
    "хьайидилай": [
        "happened.AOR-AOP-DIR-TEMP-AOP"
    ],
    "хьайила": [
        "happened-AOP-TEMP",
        "be-AOP-TEMP"
    ],
    "хьайитӀа": [
        "born-COND",
        "be.AOP.COND"
    ],
    "хьайитӀани": [
        "born-COND-FOC"
    ],
    "хьайла": [
        "be-PST-TEMP"
    ],
    "хьана": [
        "be-AOC",
        "be-AOR",
        "happened-AOR",
        "be",
        "being.AOC",
        "happened",
        "happened-AOC"
    ],
    "хьанава": [
        "happened-PERF"
    ],
    "хьанатӀа": [
        "be-AOR-COND"
    ],
    "хьанач": [
        "be-AOR-NEG",
        "happened-AOR-NEG"
    ],
    "хьаначтӀани": [
        "be-AOC-NEG-COND-FOC"
    ],
    "хьанаш": [
        "be-AOR-NEG"
    ],
    "хьанва": [
        "happened-PERF",
        "be-PERF"
    ],
    "хьанвади": [
        "happened-PERF-SBST"
    ],
    "хьанвай": [
        "be-PERF-PST",
        "be-PERF-PTP"
    ],
    "хьанватӀа": [
        "happened-PERF-COND"
    ],
    "хьанвач": [
        "happen-PERF-NEG"
    ],
    "хьи": [
        "that",
        "happen"
    ],
    "хьиз": [
        "happen-DAT",
        "as",
        "like"
    ],
    "хьийбур": [
        "happened-ABS.PL"
    ],
    "хьир": [
        "even"
    ],
    "хьтин": [
        "like"
    ],
    "хьуй": [
        "be-PST",
        "if.do",
        "let.it.be",
        "let.it.be.OPT",
        "if.do-PST"
    ],
    "хьурай": [
        "be.will",
        "be.will-AOP"
    ],
    "хьухь": [
        "be.IMPV",
        "be"
    ],
    "цавариз": [
        "air.from.off-PL-ERG-DAT"
    ],
    "цай": [
        "fire"
    ],
    "цацарив": [
        "thorns-OBL-ADESS"
    ],
    "цвана": [
        "put.in.AOC-AOR"
    ],
    "це": [
        "order.IMPV"
    ],
    "цех": [
        "wood.shop"
    ],
    "цехер": [
        "wood.shops"
    ],
    "цехера": [
        "wood.shops-ERG"
    ],
    "ци": [
        "why"
    ],
    "цуьгъвенлай": [
        "after-TEMP-AOP"
    ],
    "цуьк": [
        "flower"
    ],
    "цӀай": [
        "fire"
    ],
    "цӀайиникай": [
        "fire's-OBL-SUB-EL"
    ],
    "цӀайни": [
        "fire.and"
    ],
    "цӀийи": [
        "new"
    ],
    "цӀийиз": [
        "new-DAT"
    ],
    "цӀикьведаз": [
        "twelve-OBL-DAT"
    ],
    "цӀувад": [
        "fifteen"
    ],
    "цӀугъвена": [
        "after"
    ],
    "цӀуд": [
        "ten"
    ],
    "цӀукьуд": [
        "fourteen"
    ],
    "цӀуьд": [
        "nine"
    ],
    "цӀуьцӀуьд": [
        "nineteen"
    ],
    "ча": [
        "water",
        "give",
        "give.IMPV"
    ],
    "чав": [
        "1pl.gen-ADESS"
    ],
    "чавай": [
        "help-INELAT"
    ],
    "чаз": [
        "1pl.gen-DAT",
        "us"
    ],
    "чазди": [
        "us-DIR"
    ],
    "чак": [
        "us"
    ],
    "чал": [
        "give-SPSS",
        "water.on",
        "water-SPSS"
    ],
    "чан": [
        "dear",
        "soul"
    ],
    "чара": [
        "means",
        "divide"
    ],
    "части": [
        "unit"
    ],
    "частиниз": [
        "unit-GEN-ERG-DAT"
    ],
    "чашмиш": [
        "make.mistakes"
    ],
    "чаяр": [
        "tea",
        "tea-PL"
    ],
    "че": [
        "give"
    ],
    "чи": [
        "1pl.gen"
    ],
    "чида": [
        "know-INESS",
        "know-ENT"
    ],
    "чидай": [
        "face-FUT-PST",
        "know-AOP"
    ],
    "чиз": [
        "water-DAT"
    ],
    "чизва": [
        "know-IMPF"
    ],
    "чизвай": [
        "know-IMPF-PTP"
    ],
    "чизвайди": [
        "know-IMPF-PTP-SBST"
    ],
    "чизвач": [
        "know-IMPF-NEG"
    ],
    "чилал": [
        "ground.in-ERG-SPSS"
    ],
    "чин": [
        "know-MSD"
    ],
    "чина": [
        "face-OBL",
        "face-ERG"
    ],
    "чипин": [
        "themselves-ERG-GEN"
    ],
    "чипни": [
        "themselves-FOC"
    ],
    "чир": [
        "knowledge"
    ],
    "чир~хьана": [
        "know-BE-AOR"
    ],
    "чира": [
        "separated"
    ],
    "чирадаз": [
        "another.to-ERG-DAT"
    ],
    "чирна": [
        "know-AOR"
    ],
    "чирчадай": [
        "cook-ENT-PTP"
    ],
    "чкадай": [
        "place-INELAT"
    ],
    "чкадал": [
        "place-INESS-SPSS",
        "place-OBL-SPSS"
    ],
    "чкадиз": [
        "place-OBL-DAT"
    ],
    "чкадикай": [
        "place-OBL-SUB-EL"
    ],
    "чкадлай": [
        "place-ERG-SPSS-EL",
        "place-ERG-SPSS-INELAT"
    ],
    "чна": [
        "1pl.erg"
    ],
    "чпиз~чпиз~мукьвал": [
        "THEMSELVES.ASSOCIATED"
    ],
    "чпин": [
        "their.own"
    ],
    "чубан": [
        "shepherd"
    ],
    "чубандив": [
        "shepherd-DIR-AD"
    ],
    "чубандивай": [
        "shepherd-ERG-AD-EL"
    ],
    "чугъун": [
        "find"
    ],
    "чун": [
        "1pl.abs"
    ],
    "чурчазвайди": [
        "cook-IMPF-PTP-SBST"
    ],
    "чуь": [
        "your"
    ],
    "чуьгъвена": [
        "after"
    ],
    "чуьгъена": [
        "end.at"
    ],
    "чуьгъенал": [
        "after"
    ],
    "чуьдиз": [
        "your-DIR-DAT"
    ],
    "чуьнуьх": [
        "steal.INF"
    ],
    "чуьнуьх~хьана": [
        "HID-AOR"
    ],
    "чуьнуьхарзава": [
        "steal-AOP-IMPF"
    ],
    "чӀавалди": [
        "time-ERG-SPSS-DIR"
    ],
    "чӀаварай": [
        "time-PL-ERG-INELAT"
    ],
    "чӀавуз": [
        "time.in",
        "time-ERG-DAT",
        "time-DAT"
    ],
    "чӀавузни": [
        "time.in-Q"
    ],
    "чӀал": [
        "language"
    ],
    "чӀалалди": [
        "language-OBL-SUPER-DIR"
    ],
    "чӀалах": [
        "belivie"
    ],
    "чӀалах~жеда": [
        "BELIVED.ENT-INESS"
    ],
    "чӀахмахдин": [
        "flint.from-DIR-GEN"
    ],
    "чӀехи": [
        "great"
    ],
    "чӀувал": [
        "time.of"
    ],
    "чӀугнава": [
        "draw.INF-PERF"
    ],
    "чӀулав": [
        "black"
    ],
    "ша": [
        "come"
    ],
    "шагьвар": [
        "wind"
    ],
    "шад": [
        "happy"
    ],
    "шапӀаяр": [
        "puppy-PL"
    ],
    "шегьердиз": [
        "city-DIR-DAT",
        "city-OBL-DAT"
    ],
    "шеир": [
        "poem"
    ],
    "шеирар": [
        "poem-PL"
    ],
    "шей": [
        "thing"
    ],
    "шейер": [
        "thing-PL"
    ],
    "шейэрив": [
        "thing-PL-OBL-ADESS"
    ],
    "шехьзава": [
        "cry-IMPF"
    ],
    "шеъ": [
        "thing"
    ],
    "шив": [
        "steed"
    ],
    "шиврехъ": [
        "steed.under-POESS"
    ],
    "шикил": [
        "picture"
    ],
    "шикилда": [
        "picture-INESS"
    ],
    "шофердиз": [
        "driver-DIR-DAT"
    ],
    "шумуд": [
        "more"
    ],
    "шумудрахъ": [
        "more-PL-OBL-POESS"
    ],
    "шуькуьр": [
        "thanks"
    ],
    "ыы": [
        "uh"
    ],
    "эвел": [
        "before"
    ],
    "эвера": [
        "call.IMPV"
    ],
    "эверда": [
        "call.IMPV-ENT"
    ],
    "эверна": [
        "call-AOR",
        "call-AOC",
        "call.IMPV-AOC"
    ],
    "эвеца": [
        "get.down.IMPV"
    ],
    "эвецӀна": [
        "went.down-AOR",
        "going.down.AOC-AOR"
    ],
    "эвецӀнаша": [
        "going.down.AOC-AOR-NEG"
    ],
    "эвицӀ~хъийа": [
        "COME.DOWN"
    ],
    "эвицӀ~хъувуна": [
        "CAME.DOWN-AOR"
    ],
    "эвицӀна": [
        "COME.DOWN-AOR"
    ],
    "эвлендирмишна": [
        "married-AOR"
    ],
    "эгекьайла": [
        "approach-AOP-TEMP"
    ],
    "эгер": [
        "if"
    ],
    "эдалет": [
        "justice"
    ],
    "эквез": [
        "look.after-DAT"
    ],
    "экеча": [
        "come.out"
    ],
    "экечӀзавай": [
        "climbing-IMPF-PTP"
    ],
    "экуьнелди": [
        "morning-OBL-SUPER-DIR"
    ],
    "экъведа": [
        "walk-FUT"
    ],
    "экъвена": [
        "walk-AOR"
    ],
    "экъечӀа": [
        "go"
    ],
    "эламетар": [
        "sings-PL"
    ],
    "элкведиз": [
        "country-ERG-DAT"
    ],
    "элкъвена": [
        "turns-AOR",
        "turns-AOC"
    ],
    "элкъуьрнин": [
        "give.back-FOC-GEN"
    ],
    "элчиярни": [
        "matchmakers.also-PL-AND"
    ],
    "энциклопедияйар": [
        "encyclopedis-PL"
    ],
    "эрзе": [
        "statement"
    ],
    "эрмени": [
        "armenian"
    ],
    "эрменидин": [
        "armenian-ERG-GEN"
    ],
    "эрменидихъ": [
        "armenian-DIR-POESS"
    ],
    "эскервиле": [
        "military.service-INESS"
    ],
    "эскервилиз": [
        "military.service-PL-DAT"
    ],
    "эх": [
        "patience"
    ],
    "эхир": [
        "after.all"
    ],
    "эхтилат": [
        "story"
    ],
    "эхтилатарна": [
        "talking-AOR"
    ],
    "эхцигкъия": [
        "put.again"
    ],
    "эхьир": [
        "in."
    ],
    "эцек": [
        "put"
    ],
    "эцекна": [
        "put-AOR"
    ],
    "эциг": [
        "put.IMPV"
    ],
    "эцигда": [
        "put.IMPV-ENT"
    ],
    "эцигнава": [
        "put.IMPV-PERF"
    ],
    "югъ": [
        "day"
    ],
    "юлдаш": [
        "friend"
    ],
    "юлдашари": [
        "friend-PL-ERG"
    ],
    "юлдашди": [
        "friend-DIR"
    ],
    "юлдашдин": [
        "friend-ERG-GEN"
    ],
    "юруьмуш": [
        "tired"
    ],
    "я": [
        "oh",
        "or",
        "was",
        "cop"
    ],
    "я~тӀа": [
        "cop-COND"
    ],
    "яб~акалнама": [
        "HEARD-PERF.CONT"
    ],
    "явашдак": [
        "slowly"
    ],
    "явашдиказ": [
        "slowly"
    ],
    "ягъ": [
        "strike.IMPV"
    ],
    "ягъайтавур": [
        "shoot"
    ],
    "ягъан": [
        "hit-HORT"
    ],
    "ягъана": [
        "hit-AOR"
    ],
    "ягъун": [
        "strike-MSD"
    ],
    "яд": [
        "water"
    ],
    "яда": [
        "or"
    ],
    "ядни": [
        "water-AND"
    ],
    "язва": [
        "cop-IMPF"
    ],
    "язух": [
        "pity"
    ],
    "ял": [
        "breath"
    ],
    "ялна": [
        "breath-AOR"
    ],
    "яма": [
        "is"
    ],
    "яман": [
        "was"
    ],
    "яни": [
        "cop-FOC",
        "cop.Q",
        "cop-Q"
    ],
    "яр": [
        "sweetheart"
    ],
    "яраб": [
        "I.wonder"
    ],
    "яратмиша": [
        "create"
    ],
    "яргъай": [
        "far"
    ],
    "яргъал": [
        "far"
    ],
    "яргъалай": [
        "far-ERG-INELAT"
    ],
    "ярдиз": [
        "sweetheart-ERG-DAT",
        "sweetheart-DIR-DAT"
    ],
    "яру": [
        "red"
    ],
    "ярх~хьай": [
        "TURNED.AROUND-AOP"
    ],
    "ятӀа": [
        "was-COND",
        "cop-COND"
    ],
    "ятӀани": [
        "is.if"
    ],
    "яхцӀур": [
        "fourty"
    ],
    "яхъ": [
        "take"
    ],
    "яцаривай": [
        "bulls-PL-ERG-AD-EL"
    ],
    "яшайиш": [
        "living.person"
    ],
    "–": [
        "–"
    ],
    "—": [
        "—"
    ],
    "…": [
        "…"
    ]
}